Workbook

Sheet ①現状の資本構成
B1: WineBank 資本構成（2026年1月末 割当後）
B2: 出典：202602 資本政策案。FD＝潜在株式（ストックオプション）考慮後。単位：株
B4: 【1】株主構成
B5: 株主 | C5: 発行済 株数 | D5: 比率 | E5: FD 株数 | F5: FD 比率 | G5: 区分
B6: 中野邦人 | C6: 3413 | D6: =C6/$C$18 | E6: 3413 | F6: =E6/$E$18 | G6: 中野ブロック
B7: 中野邦人 SO相当分 | C7: 0 | D7: =C7/$C$18 | E7: 170 | F7: =E7/$E$18 | G7: 中野ブロック
B8: Crown Jewel box LLC SO相当分 | C8: 0 | D8: =C8/$C$18 | E8: 287 | F8: =E8/$E$18 | G8: 中野ブロック
B9: 株式会社スペースバンク | C9: 45 | D9: =C9/$C$18 | E9: 91 | F9: =E9/$E$18 | G9: 中野ブロック
B10: マネーフォワードベンチャーズ（Hirac Fund 2号） | C10: 749 | D10: =C10/$C$18 | E10: 749 | F10: =E10/$E$18 | G10: 外部
B11: 株式会社Private BANK | C11: 375 | D11: =C11/$C$18 | E11: 375 | F11: =E11/$E$18 | G11: 外部
B12: 戸高薫 SO相当分 | C12: 0 | D12: =C12/$C$18 | E12: 200 | F12: =E12/$E$18 | G12: 外部
B13: 小田垣栄司 | C13: 200 | D13: =C13/$C$18 | E13: 200 | F13: =E13/$E$18 | G13: 外部
B14: 株式会社ベクトル | C14: 157 | D14: =C14/$C$18 | E14: 157 | F14: =E14/$E$18 | G14: 外部
B15: 個人投資家様 | C15: 90 | D15: =C15/$C$18 | E15: 90 | F15: =E15/$E$18 | G15: 外部
B16: 寺田倉庫株式会社 | C16: 52 | D16: =C16/$C$18 | E16: 52 | F16: =E16/$E$18 | G16: 外部
B17: 執行役員・従業員・その他関係者等 | C17: 0 | D17: =C17/$C$18 | E17: 6 | F17: =E17/$E$18 | G17: 外部
B18: 合計 | C18: =SUM(C6:C17) | D18: 1 | E18: =SUM(E6:E17) | F18: 1
B20: 中野ブロック 小計 | C20: =SUM(C6:C9) | D20: =C20/C18 | E20: =SUM(E6:E9) | F20: =E20/E18 | G20: 中野邦人＋100%保有法人（Crown Jewel box・スペースバンク）
B21: 外部株主 小計 | C21: =C18-C20 | D21: =C21/C18 | E21: =E18-E20 | F21: =E21/E18
B23: 【2】直近ラウンドの条件
B24: 直近発行価額（2026年1月ラウンド） | C24: 450000 | G24: 第三者割当 357株・調達160,650千円
B25: ポストマネー評価額 | C25: =E18*C24 | G25: FD株数 × 発行価額
B26: 中野ブロックの持分価値 | C26: =E20*C24 | G26: FD株数 × 発行価額
B28: ※Crown Jewel box は資本政策表上「Clown Jewel box LLC」と表記。上場審査資料では登記名との一致が必要です。

Sheet ②希薄化余地
B1: 「中野ブロック50%」をどこで測るか
B2: 戦略ラウンドの直後で50%にすると、上場時の公募増資でさらに希薄化し50%を割ります。
B4: 【1】前提
B5: 現在のFD株数 | C5: ='①現状の資本構成'!E18 | G5: ①現状の資本構成から参照
B6: 中野ブロック FD株数 | C6: ='①現状の資本構成'!E20 | G6: ①現状の資本構成から参照
B7: 中野ブロック 現在比率 | C7: =C6/C5
B8: 流通株式適格（既存外部・10%未満かつ非役員） | C8: 1423 | G8: MFV749＋Private BANK375＋ベクトル157＋寺田52＋個人90
B9: 上場時 流通株式比率の要件 | C9: 0.25 | G9: 東証グロース。10%以上の株主・役員等の保有分は流通株式から除外
B10: 直近発行価額 | C10: ='①現状の資本構成'!C24 | G10: ①現状の資本構成から参照
B12: 【2】戦略ラウンドの規模別シミュレーション ※上場時に流通25%を満たす最小公募を置いた場合
B13: 戦略ラウンド 発行株数 | C13: ラウンド直後の 新株主比率 | D13: ラウンド直後の 中野ブロック | E13: 上場時に必要な 公募株数 | F13: 上場時の 中野ブロック
B14: 0 | C14: =B14/($C$5+B14) | D14: =$C$6/($C$5+B14) | E14: =MAX(0,ROUNDUP((($C$9*($C$5+B14))-$C$8)/(1-$C$9),0)) | F14: =$C$6/($C$5+B14+E14)
B15: 600 | C15: =B15/($C$5+B15) | D15: =$C$6/($C$5+B15) | E15: =MAX(0,ROUNDUP((($C$9*($C$5+B15))-$C$8)/(1-$C$9),0)) | F15: =$C$6/($C$5+B15+E15)
B16: 900 | C16: =B16/($C$5+B16) | D16: =$C$6/($C$5+B16) | E16: =MAX(0,ROUNDUP((($C$9*($C$5+B16))-$C$8)/(1-$C$9),0)) | F16: =$C$6/($C$5+B16+E16)
B17: 1200 | C17: =B17/($C$5+B17) | D17: =$C$6/($C$5+B17) | E17: =MAX(0,ROUNDUP((($C$9*($C$5+B17))-$C$8)/(1-$C$9),0)) | F17: =$C$6/($C$5+B17+E17)
B18: 1500 | C18: =B18/($C$5+B18) | D18: =$C$6/($C$5+B18) | E18: =MAX(0,ROUNDUP((($C$9*($C$5+B18))-$C$8)/(1-$C$9),0)) | F18: =$C$6/($C$5+B18+E18) | G18: ★上場時に中野ブロック50%超を維持できる上限
B19: 1600 | C19: =B19/($C$5+B19) | D19: =$C$6/($C$5+B19) | E19: =MAX(0,ROUNDUP((($C$9*($C$5+B19))-$C$8)/(1-$C$9),0)) | F19: =$C$6/($C$5+B19+E19)
B20: 1800 | C20: =B20/($C$5+B20) | D20: =$C$6/($C$5+B20) | E20: =MAX(0,ROUNDUP((($C$9*($C$5+B20))-$C$8)/(1-$C$9),0)) | F20: =$C$6/($C$5+B20+E20)
B21: 2132 | C21: =B21/($C$5+B21) | D21: =$C$6/($C$5+B21) | E21: =MAX(0,ROUNDUP((($C$9*($C$5+B21))-$C$8)/(1-$C$9),0)) | F21: =$C$6/($C$5+B21+E21)
B23: ※黄色セル（発行株数）を変えると全列が再計算されます。
B24: ※上場時の中野ブロックは、戦略ラウンドと公募増資の二段階の希薄化を反映した値です。
B25: ※戦略株主が各10%超で保有する前提。10%未満に抑えれば流通株式に算入され、必要公募株数は減ります。

Sheet ③トランシェ比較
B1: 同じ希薄化で、いくら調達できるか
B2: 戦略ラウンドを2回に分けると、着地の持分を変えずに調達額を約1.4倍にできます。
B4: 【1】比較
C5: 案A：一括 | D5: 案B：2トランシェ | E5: 差 B−A
B6: 第1トランシェ 株数 | C6: 1500 | D6: 900
B7: 第1トランシェ 発行価額 | C7: 450000 | D7: 450000
B8: 第1トランシェ 調達額 | C8: =C6*C7 | D8: =D6*D7
B9: 第2トランシェ 株数 | C9: 0 | D9: 600
B10: 第2トランシェ 発行価額 | C10: 0 | D10: 900000
B11: 第2トランシェ 調達額 | C11: =C9*C10 | D11: =D9*D10
B12: 調達額 合計 | C12: =C8+C11 | D12: =D8+D11 | E12: =D12-C12
B13: 戦略株主 合計株数 | C13: =C6+C9 | D13: =D6+D9
B14: 上場前 総株数（FD） | C14: ='②希薄化余地'!$C$5+C13 | D14: ='②希薄化余地'!$C$5+D13
B15: 上場時に必要な公募株数 | C15: =MAX(0,ROUNDUP((('②希薄化余地'!$C$9*C14)-'②希薄化余地'!$C$8)/(1-'②希薄化余地'!$C$9),0)) | D15: =MAX(0,ROUNDUP((('②希薄化余地'!$C$9*D14)-'②希薄化余地'!$C$8)/(1-'②希薄化余地'!$C$9),0))
B16: 上場時 総株数 | C16: =C14+C15 | D16: =D14+D15
B17: 上場時 中野ブロック比率 | C17: ='②希薄化余地'!$C$6/C16 | D17: ='②希薄化余地'!$C$6/D16 | E17: =D17-C17
B19: ※案Bの第2トランシェ価額90万円は、プランD（経常＋120.4百万円）を実現した後のステップアップを想定した仮置きです。
B20: ※FY2026の着地（経常▲124.8百万円）で全量を price すると、最も不利な時点で希薄化を確定させることになります。

Sheet ④2社への割付
B1: 戦略パートナー2社への割付案（案B・合計1,500株）
B2: 各社を15%未満に抑え、持分法適用（相手側の損益取込み）を回避します。
B4: 【1】割付
C5: 第1トランシェ | D5: 第2トランシェ | E5: 合計 株数 | F5: 上場前 比率 | G5: 上場時 比率
B6: 金融・資本市場パートナー | C6: 450 | D6: 300 | E6: =C6+D6 | F6: =E6/'③トランシェ比較'!$D$14 | G6: =E6/'③トランシェ比較'!$D$16
B7: 富裕層・二次流通パートナー | C7: 450 | D7: 300 | E7: =C7+D7 | F7: =E7/'③トランシェ比較'!$D$14 | G7: =E7/'③トランシェ比較'!$D$16
B8: 合計 | C8: =SUM(C6:C7) | D8: =SUM(D6:D7) | E8: =SUM(E6:E7) | F8: =SUM(F6:F7) | G8: =SUM(G6:G7)
B10: 【2】守るべき閾値
B11: 各社 15%未満 | C11: 持分法適用（相手側が当社損益を取り込む）を回避。20%以上は原則適用、15〜20%も役員派遣等で適用され得る
B12: 2社合計 33.3%以下 | C12: 特別決議の拒否権を渡さない
B13: 上場時 中野ブロック 50%超 | C13: 戦略ラウンドと公募増資の二段階の希薄化を反映した後の水準で測る
B14: 流通株式比率 25%以上 | C14: 東証グロース。戦略株主にはロックアップと一部売出しを出資契約の時点で合意しておく

Sheet ⑤事前に潰す論点
B1: パートナー打診の前に片づけておく論点
B2: いずれもデューデリジェンスで必ず出ます。後から出ると交渉力を失います。
B4: 【1】論点
B6: 関連当事者 持分 | C6: Crown Jewel box LLC SO 287株（FD 5.0%）とスペースバンク 91株（同1.6%）の計378株・6.5%が中野氏100%保有法人。法人へのストックオプション付与は通常の設計ではなく、主幹事・監査法人から必ず論点化されます。
B8: 関連当事者 取引 | C8: FY2027計画のコンサルティング料92.5百万円は中野出資グループからの収入。銀行向けに用意した「支払能力と対価の算定根拠」の文書化を先行させ、DDの一次資料として提出できる状態にしておく。
B10: 選択肢：取り込み | C10: スペースバンク・Crown Jewel box に実体事業があるなら、株式交換または現物出資でWineBankに取り込む案がある。①関連当事者論点が消える ②中野氏の持分が増えて戦略ラウンドの希薄化を相殺できる ③事業ストーリーが1本化される。両社の事業内容・売上・純資産の確認が先。
B12: プロラタ権 | C12: マネーフォワードベンチャーズ（FD 12.9%・最大の外部株主）の引受権・希薄化防止条項の有無を投資契約で確認。パートナー探索を勧めているのは同社なので、事前に方針をすり合わせておくのが早い。
B14: 種類株の設計 | C14: 2026年1月ラウンドは種類株での調達実績あり。議決権のない種類株にすれば、中野持分を薄めずに資金を入れられ、相手側も持分法適用を避けられる。取締役会オブザーバー席＋事前承諾事項で実質的な関与を担保する。
B16: プライシングの時期 | C16: FY2026着地（経常▲124.8百万円）でバリュエーション交渉に入るのは最も不利。デューデリジェンスは今すぐ着手し、価格決定はFY2027 第1〜第2四半期の実績が出た後に置く。
B18: ワインファンドの前歴 | C18: 2016年のVIN-NET破綻（約36億円が償還不能）で日本のワインファンド市場は止まった経緯があり、どの相手からも必ず問われます。現物保管・所有権の明確化・第三者評価の3点で答えを用意する。規制業者である証券会社を株主に入れること自体が、この疑念への回答になります。

Sheet ⑥既存株主入替え
B1: 既存株主を入れ替えて強力なパートナーを迎える場合
B2: 経営陣以外の株主を買い取り、パートナーが譲受＋増資で持分を取る前提。単位：株／円
B4: 【1】株主の色分け
C5: FD 株数 | D5: FD 比率
B6: 経営陣ブロック（残留） | C6: 4367 | D6: =C6/'②希薄化余地'!$C$5 | G6: 中野ブロック3,961＋小田垣200＋戸高SO200＋従業員6
B7: うち 中野ブロック | C7: 3961 | D7: =C7/'②希薄化余地'!$C$5 | G7: 中野個人3,413＋SO170＋Crown Jewel box 287＋スペースバンク91
B8: 売却対象（外部株主） | C8: 1423 | D8: =C8/'②希薄化余地'!$C$5 | G8: MFV749＋Private BANK375＋ベクトル157＋個人90＋寺田52
B9: 買取・引受 単価（前提） | C9: 450000 | G9: 2026年1月ラウンドと同額を仮置き。ここを変えると【2】【3】が再計算されます。
B11: 【2】売却対象株主の取得原価 ※買取交渉の難易度
B12: 株主 | C12: 株数 | D12: 取得原価 合計 | E12: 取得単価 | F12: @45万での倍率 | G12: 受取額 @45万
B13: マネーフォワードベンチャーズ | C13: 749 | D13: 250095000 | E13: =D13/C13 | F13: =C13*$C$9/D13 | G13: =C13*$C$9
B14: 株式会社Private BANK | C14: 375 | D14: 18750000 | E14: =D14/C14 | F14: =C14*$C$9/D14 | G14: =C14*$C$9
B15: 株式会社ベクトル | C15: 157 | D15: 30144000 | E15: =D15/C15 | F15: =C15*$C$9/D15 | G15: =C15*$C$9
B16: 個人投資家様 | C16: 90 | D16: 40500000 | E16: =D16/C16 | F16: =C16*$C$9/D16 | G16: =C16*$C$9
B17: 寺田倉庫株式会社 | C17: 52 | D17: 9984000 | E17: =D17/C17 | F17: =C17*$C$9/D17 | G17: =C17*$C$9
B18: 合計 | C18: =SUM(C13:C17) | D18: =SUM(D13:D17) | G18: =SUM(G13:G17)
B20: ※取得原価の大半が低い株主（Private BANK 9.0倍・ベクトル/寺田 2.3倍）は売却に応じやすい。
B21: ※実質的な交渉相手はマネーフォワードベンチャーズ1社。@45万では1.35倍にとどまり、価格を押してくる可能性が高い。
B22: ※個人投資家様90株は2026年1月に@45万で参加したばかりで簿価売却となるため、別途の配慮が要る。
B24: 【3】パートナー持分別の投下額 ※外部1,423株の譲受＋増資
B25: パートナー 目標持分 | C25: 必要な増資 株数 | D25: 譲受＋増資の 投下総額 | E25: 上場前 総株数 | F25: 中野ブロック 比率
B26: 0.334 | C26: =($B26*'②希薄化余地'!$C$5-$C$8)/(1-$B26) | D26: =($C$8+C26)*$C$9 | E26: ='②希薄化余地'!$C$5+C26 | F26: ='②希薄化余地'!$C$6/E26 | G26: 拒否権ライン。持分法適用で相手のPLに乗る
B27: 0.4 | C27: =($B27*'②希薄化余地'!$C$5-$C$8)/(1-$B27) | D27: =($C$8+C27)*$C$9 | E27: ='②希薄化余地'!$C$5+C27 | F27: ='②希薄化余地'!$C$6/E27 | G27: 筆頭株主は中野氏のまま。実質的な共同経営
B28: 0.501 | C28: =($B28*'②希薄化余地'!$C$5-$C$8)/(1-$B28) | D28: =($C$8+C28)*$C$9 | E28: ='②希薄化余地'!$C$5+C28 | F28: ='②希薄化余地'!$C$6/E28 | G28: 連結子会社化。上場は親子上場となる
B30: ※投下総額は@45万換算。支配権プレミアムを乗せれば増え、FY2026の着地を理由に値引きされれば減ります。
B32: 【4】過半数を渡す場合に必ず起きること
B33: 親子上場 | C33: 上場会社が過半数を持つと、WineBankの上場は親子上場になる。東証は支配株主を有する上場会社へのガバナンス要求を強めており、上場審査では親会社からの独立性が厳しく問われる。実務的には、出口はIPOではなく将来の完全子会社化（M&A）に寄る。
B34: 赤字の連結 | C34: 過半数を取った相手はWineBankの損益を全部取り込む。FY2026の経常▲124.8百万円を連結する判断は上場会社にとって重い。プランDの黒字化を確認してからのほうが、相手は動きやすい。
B35: IPOを残す道 | C35: パートナーを33.4〜49%にとどめれば親子上場にはならず、持分法で相手のPLには乗る。「本気度」は比率ではなく、独占提携・役員派遣・相手の営業目標への組み込み・未達時のラチェットで担保する。
B36: PEという選択肢 | C36: 既存株主を全部買い取り、経営改革し、数年でIPOに持っていくのはプライベートエクイティの標準的な仕事。PEが40%前後、事業会社が10〜15%で並走する二階建てなら、株主整理・経営改革・IPOの3つを同時に満たせる。
