Workbook

Sheet ①サマリー
B1: FY2027（2027年9月期）事業計画
B2: ベース：2026年4-7月の実績月平均（不採算3店舗の撤退後）。単位：円（税別）
B4: 科目 | C4: 横ばい実力値 （参考） | D4: プランD メインシナリオ | E4: プランE 上振れシナリオ | F4: コメント
B5: 既存事業 売上 | C5: ='②前提'!$D$6 | D5: ='②前提'!$C$29 | E5: =('②前提'!$C$29+'②前提'!$C$32) | F5: Dは前期・今期の売上平均。Eは私募＋オークション300を上積み
B6: ＋上乗せ案件 | C6: 0 | D6: ='②前提'!$C$18 | E6: ='②前提'!$C$18 | F6: コンサルティング料82.5＋クルーザー×ワイン事業20.0
B7: ＋現物出資 追加計上 | C7: 0 | D7: ='②前提'!$C$22 | E7: ='②前提'!$C$22 | F7: 売上計上しない前提のため0。粗利15.0のみ計上
B8: 売上高 合計 | C8: ='②前提'!$D$6 | D8: =('②前提'!$C$29+'②前提'!$C$18+'②前提'!$C$22) | E8: =('②前提'!$C$29+'②前提'!$C$32+'②前提'!$C$18+'②前提'!$C$22)
B9: 売上総利益 | C9: ='②前提'!$D$7 | D9: =('②前提'!$D$7+'②前提'!$C$30*'②前提'!$C$31+'②前提'!$C$18+'②前提'!$C$23) | E9: =('②前提'!$D$7+'②前提'!$C$30*'②前提'!$C$31+'②前提'!$C$18+'②前提'!$C$23+'②前提'!$C$32*'②前提'!$C$31) | F9: 差額売上・追加売上の粗利率は保守的に30%
B10: 総合粗利率 | C10: =C9/C8 | D10: =D9/D8 | E10: =E9/E8
B11: 販管費 | C11: ='②前提'!$D$8 | D11: ='②前提'!$D$8 | E11: ='②前提'!$D$8 | F11: 2026/04-07実績の月平均×12
B12: 営業利益 | C12: =C9-C11 | D12: =D9-D11 | E12: =E9-E11
B13: 営業外費用 | C13: ='②前提'!$C$35 | D13: ='②前提'!$C$35 | E13: ='②前提'!$C$35 | F13: みずほ銀行への返済により支払利息が減少
B14: 経常利益 | C14: =C12-C13 | D14: =D12-D13 | E14: =E12-E13
B15: 法人税等 | C15: 0 | D15: =MAX(0,D14-'②前提'!$C$36)*'②前提'!$C$37 | E15: =MAX(0,E14-'②前提'!$C$36)*'②前提'!$C$37 | F15: 繰越欠損金139.9百万円を超える所得に課税
B16: 当期純利益 | C16: =C14-C15 | D16: =D14-D15 | E16: =E14-E15
B18: 【判定】
B19: 横ばい実力値：2026年4-7月の実績をそのまま延ばすと営業利益▲79.5・経常利益▲91.5百万円。
B20: プランD：既存事業を前期・今期の売上平均656.4百万円に戻し、契約ベースの上乗せ案件102.5百万円と
B21: 現物出資の追加粗利15.0百万円を加算。売上758.9・営業＋87.2・経常＋75.2百万円。
B22: プランE：Dに私募ファンド＋オークションで300百万円（粗利率30%）を上積み。
B23: 売上1,058.9・営業＋177.2・経常＋165.2百万円。繰越欠損金超過分に法人税8.6百万円。
B25: ※FY2026の着地は営業利益＋1.0・経常▲11.6百万円。ここからの改善幅はDで＋86.2百万円。
B26: ※アピシウスM&A仲介20.0とコンサルティング料10.0の計30.0百万円はFY2026に前倒し計上済みのため、
B27: 今期の上乗せ案件は132.5→102.5百万円に減っています。
B28: ※期首の商品在庫は187.4百万円（従来モデルの420百万円から大幅減）。仕入計画は④をご参照ください。
B29: ※期首現預金は仮に30百万円。2026/09末の着地値への差し替えが必要です。

Sheet ②前提
B1: FY2027（2027年9月期）事業計画 前提条件
B2: 黄色＝入力セル。ベースは2026年4-7月の実績月平均（不採算3店舗の撤退後）。単位：円（税別）
B4: 【1】ベース：再編後の実力値（2026/04-07 実績の月平均）
B5: 項目 | C5: 月次平均 | D5: 年換算
B6: 売上 | C6: 41014063 | D6: =C6*12 | E6: 4月32.5／5月35.5／6月32.9／7月63.1百万円の平均
B7: 売上総利益 | C7: 18997735 | D7: =C7*12 | E7: 同4か月の平均。粗利率46.3%
B8: 販管費 | C8: 25624504 | D8: =C8*12 | E8: 同4か月の平均。2026/03以前は撤退3店舗を含むため除外
B9: 売上総利益率 | C9: =C7/C6
B10: 横ばい延伸時の営業利益（年） | D10: =D7-D8 | E10: 何もしなければこの水準。ここからの積み上げが計画です。
B12: 【2】上乗せ案件（FY2027）
B13: 案件 | C13: 金額 | D13: 計上月
B14: コンサルティング料 間接グループ5社 | C14: 80000000 | D14: 0 | E14: 12か月按分。中野出資のグループ会社5社
B15: コンサルティング料 Thierry Marx | C15: 2500000 | D15: 0 | E15: 12か月按分。2026年4月開業
B16: クルーザー×ワイン事業 1回目 | C16: 10000000 | D16: 6 | E16: 6＝2027年3月
B17: クルーザー×ワイン事業 2回目 | C17: 10000000 | D17: 12 | E17: 12＝2027年9月
B18: 合計 | C18: =SUM(C14:C17) | E18: ★アピシウスM&A仲介20.0とコンサルティング料10.0の計30.0百万円はFY2026に前倒し計上済みのため、今期は計上しません。
B19: （参考）前回計画の上乗せ案件 | C19: 132500000 | E19: 132.5 → 102.5百万円。差30.0百万円が前倒し分です。
B21: 【3】私募ファンド 現物出資分の追加計上
B22: 追加計上する売上 | C22: 0 | E22: ★FY2026と同じ建て付け（売上計上せず）とする場合は0。売上を計上する場合は300,000,000を入力してください。
B23: 追加計上する粗利 | C23: 15000000 | E23: 現物出資3億円に対する追加5%。FY2026の10%（30百万円）とあわせて計15%
B24: 計上月（1〜12） | C24: 12 | E24: 12＝2027年9月
B26: 【4】プランD・Eの前提
B27: FY2025 売上高（実績） | C27: 752864901 | E27: 決算報告書 第54期
B28: FY2026 既存事業 売上高（着地） | C28: 559914185 | E28: 10か月実績444.9＋8-9月115.0百万円。私募600・前倒し30は一過性のため除外
B29: 前期・今期の売上平均 | C29: =(C27+C28)/2 | E29: プランDの既存事業売上。新たな成長を前提にしていません
B30: 差額売上（横ばいからの上積み） | C30: =C29-D6 | E30: 売上平均−横ばい年換算
B31: 差額売上の粗利率 | C31: 0.3 | E31: FY2025 26.8%・FY2026実績を踏まえ保守的に30%
B32: プランE 追加売上（私募＋オークション） | C32: 300000000 | E32: FY2026に私募で実際に組成した規模と同水準
B34: 【5】その他
B35: 営業外費用（年額） | C35: 12000000 | E35: FY2026着地13.0百万円。みずほ銀行への返済により支払利息が減少
B36: 繰越欠損金 残高（期首） | C36: 139865685 | E36: FY2025 127.4＋FY2026 12.5百万円。FY2026着地予想より
B37: 法人実効税率 | C37: 0.34 | E37: 繰越欠損金を使い切った後の課税所得に適用
B38: 期首 現預金 | C38: 30000000 | E38: ★2026/09末の着地値に差し替えてください。私募3億の入金時期とみずほ返済の実行で変動します
B39: 期首 商品在庫 | C39: 187411335 | E39: FY2026着地予想より。従来モデルの420百万円から大きく下がっています
B40: 年間 ワイン仕入 | C40: 450000000 | E40: ★仕入方針。割当維持のため落とさない前提

Sheet ③月次推移表
B1: FY2027 月次推移表 － プランD
B2: 既存事業は均等按分。上乗せ案件は②前提で指定した月に計上（計上月0＝12か月按分）。単位：円（税別）
B4: 科目 | C4: 2026/10 | D4: 2026/11 | E4: 2026/12 | F4: 2027/01 | G4: 2027/02 | H4: 2027/03 | I4: 2027/04 | J4: 2027/05 | K4: 2027/06 | L4: 2027/07 | M4: 2027/08 | N4: 2027/09 | O4: 通期
B5: 【売上高】
B6: 既存事業 売上 | C6: ='②前提'!$C$29/12 | D6: ='②前提'!$C$29/12 | E6: ='②前提'!$C$29/12 | F6: ='②前提'!$C$29/12 | G6: ='②前提'!$C$29/12 | H6: ='②前提'!$C$29/12 | I6: ='②前提'!$C$29/12 | J6: ='②前提'!$C$29/12 | ... N6: ='②前提'!$C$29/12 | O6: =SUM(C6:N6)
B7: ＋上乗せ案件 | C7: =IF('②前提'!$C$14=0,0,IF('②前提'!$D$14=0,'②前提'!$C$14/12,IF('②前提'!$D$14=1,'②前提'!$C$14,0)))+IF('②前提'!$C$15=0,0,IF('②前提'!$D$15=0,'②前提'!$C$15/12,IF('②前提'!$D$15=1,'②前提'!$C$15,0)))+IF('②前提'!$C$16=0,0,IF('②前提'!$D$16=0,'②前提'!$C$16/12,IF('②前提'!$D$16=1,'②前提'!$C$16,0)))+IF('②前提'!$C$17=0,0,IF('②前提'!$D$17=0,'②前提'!$C$17/12,IF('②前提'!$D$17=1,'②前提'!$C$17,0))) | D7: =IF('②前提'!$C$14=0,0,IF('②前提'!$D$14=0,'②前提'!$C$14/12,IF('②前提'!$D$14=2,'②前提'!$C$14,0)))+IF('②前提'!$C$15=0,0,IF('②前提'!$D$15=0,'②前提'!$C$15/12,IF('②前提'!$D$15=2,'②前提'!$C$15,0)))+IF('②前提'!$C$16=0,0,IF('②前提'!$D$16=0,'②前提'!$C$16/12,IF('②前提'!$D$16=2,'②前提'!$C$16,0)))+IF('②前提'!$C$17=0,0,IF('②前提'!$D$17=0,'②前提'!$C$17/12,IF('②前提'!$D$17=2,'②前提'!$C$17,0))) | E7: =IF('②前提'!$C$14=0,0,IF('②前提'!$D$14=0,'②前提'!$C$14/12,IF('②前提'!$D$14=3,'②前提'!$C$14,0)))+IF('②前提'!$C$15=0,0,IF('②前提'!$D$15=0,'②前提'!$C$15/12,IF('②前提'!$D$15=3,'②前提'!$C$15,0)))+IF('②前提'!$C$16=0,0,IF('②前提'!$D$16=0,'②前提'!$C$16/12,IF('②前提'!$D$16=3,'②前提'!$C$16,0)))+IF('②前提'!$C$17=0,0,IF('②前提'!$D$17=0,'②前提'!$C$17/12,IF('②前提'!$D$17=3,'②前提'!$C$17,0))) | F7: =IF('②前提'!$C$14=0,0,IF('②前提'!$D$14=0,'②前提'!$C$14/12,IF('②前提'!$D$14=4,'②前提'!$C$14,0)))+IF('②前提'!$C$15=0,0,IF('②前提'!$D$15=0,'②前提'!$C$15/12,IF('②前提'!$D$15=4,'②前提'!$C$15,0)))+IF('②前提'!$C$16=0,0,IF('②前提'!$D$16=0,'②前提'!$C$16/12,IF('②前提'!$D$16=4,'②前提'!$C$16,0)))+IF('②前提'!$C$17=0,0,IF('②前提'!$D$17=0,'②前提'!$C$17/12,IF('②前提'!$D$17=4,'②前提'!$C$17,0))) | G7: =IF('②前提'!$C$14=0,0,IF('②前提'!$D$14=0,'②前提'!$C$14/12,IF('②前提'!$D$14=5,'②前提'!$C$14,0)))+IF('②前提'!$C$15=0,0,IF('②前提'!$D$15=0,'②前提'!$C$15/12,IF('②前提'!$D$15=5,'②前提'!$C$15,0)))+IF('②前提'!$C$16=0,0,IF('②前提'!$D$16=0,'②前提'!$C$16/12,IF('②前提'!$D$16=5,'②前提'!$C$16,0)))+IF('②前提'!$C$17=0,0,IF('②前提'!$D$17=0,'②前提'!$C$17/12,IF('②前提'!$D$17=5,'②前提'!$C$17,0))) | H7: =IF('②前提'!$C$14=0,0,IF('②前提'!$D$14=0,'②前提'!$C$14/12,IF('②前提'!$D$14=6,'②前提'!$C$14,0)))+IF('②前提'!$C$15=0,0,IF('②前提'!$D$15=0,'②前提'!$C$15/12,IF('②前提'!$D$15=6,'②前提'!$C$15,0)))+IF('②前提'!$C$16=0,0,IF('②前提'!$D$16=0,'②前提'!$C$16/12,IF('②前提'!$D$16=6,'②前提'!$C$16,0)))+IF('②前提'!$C$17=0,0,IF('②前提'!$D$17=0,'②前提'!$C$17/12,IF('②前提'!$D$17=6,'②前提'!$C$17,0))) | I7: =IF('②前提'!$C$14=0,0,IF('②前提'!$D$14=0,'②前提'!$C$14/12,IF('②前提'!$D$14=7,'②前提'!$C$14,0)))+IF('②前提'!$C$15=0,0,IF('②前提'!$D$15=0,'②前提'!$C$15/12,IF('②前提'!$D$15=7,'②前提'!$C$15,0)))+IF('②前提'!$C$16=0,0,IF('②前提'!$D$16=0,'②前提'!$C$16/12,IF('②前提'!$D$16=7,'②前提'!$C$16,0)))+IF('②前提'!$C$17=0,0,IF('②前提'!$D$17=0,'②前提'!$C$17/12,IF('②前提'!$D$17=7,'②前提'!$C$17,0))) | J7: =IF('②前提'!$C$14=0,0,IF('②前提'!$D$14=0,'②前提'!$C$14/12,IF('②前提'!$D$14=8,'②前提'!$C$14,0)))+IF('②前提'!$C$15=0,0,IF('②前提'!$D$15=0,'②前提'!$C$15/12,IF('②前提'!$D$15=8,'②前提'!$C$15,0)))+IF('②前提'!$C$16=0,0,IF('②前提'!$D$16=0,'②前提'!$C$16/12,IF('②前提'!$D$16=8,'②前提'!$C$16,0)))+IF('②前提'!$C$17=0,0,IF('②前提'!$D$17=0,'②前提'!$C$17/12,IF('②前提'!$D$17=8,'②前提'!$C$17,0))) | K7: =IF('②前提'!$C$14=0,0,IF('②前提'!$D$14=0,'②前提'!$C$14/12,IF('②前提'!$D$14=9,'②前提'!$C$14,0)))+IF('②前提'!$C$15=0,0,IF('②前提'!$D$15=0,'②前提'!$C$15/12,IF('②前提'!$D$15=9,'②前提'!$C$15,0)))+IF('②前提'!$C$16=0,0,IF('②前提'!$D$16=0,'②前提'!$C$16/12,IF('②前提'!$D$16=9,'②前提'!$C$16,0)))+IF('②前提'!$C$17=0,0,IF('②前提'!$D$17=0,'②前提'!$C$17/12,IF('②前提'!$D$17=9,'②前提'!$C$17,0))) | L7: =IF('②前提'!$C$14=0,0,IF('②前提'!$D$14=0,'②前提'!$C$14/12,IF('②前提'!$D$14=10,'②前提'!$C$14,0)))+IF('②前提'!$C$15=0,0,IF('②前提'!$D$15=0,'②前提'!$C$15/12,IF('②前提'!$D$15=10,'②前提'!$C$15,0)))+IF('②前提'!$C$16=0,0,IF('②前提'!$D$16=0,'②前提'!$C$16/12,IF('②前提'!$D$16=10,'②前提'!$C$16,0)))+IF('②前提'!$C$17=0,0,IF('②前提'!$D$17=0,'②前提'!$C$17/12,IF('②前提'!$D$17=10,'②前提'!$C$17,0))) | M7: =IF('②前提'!$C$14=0,0,IF('②前提'!$D$14=0,'②前提'!$C$14/12,IF('②前提'!$D$14=11,'②前提'!$C$14,0)))+IF('②前提'!$C$15=0,0,IF('②前提'!$D$15=0,'②前提'!$C$15/12,IF('②前提'!$D$15=11,'②前提'!$C$15,0)))+IF('②前提'!$C$16=0,0,IF('②前提'!$D$16=0,'②前提'!$C$16/12,IF('②前提'!$D$16=11,'②前提'!$C$16,0)))+IF('②前提'!$C$17=0,0,IF('②前提'!$D$17=0,'②前提'!$C$17/12,IF('②前提'!$D$17=11,'②前提'!$C$17,0))) | N7: =IF('②前提'!$C$14=0,0,IF('②前提'!$D$14=0,'②前提'!$C$14/12,IF('②前提'!$D$14=12,'②前提'!$C$14,0)))+IF('②前提'!$C$15=0,0,IF('②前提'!$D$15=0,'②前提'!$C$15/12,IF('②前提'!$D$15=12,'②前提'!$C$15,0)))+IF('②前提'!$C$16=0,0,IF('②前提'!$D$16=0,'②前提'!$C$16/12,IF('②前提'!$D$16=12,'②前提'!$C$16,0)))+IF('②前提'!$C$17=0,0,IF('②前提'!$D$17=0,'②前提'!$C$17/12,IF('②前提'!$D$17=12,'②前提'!$C$17,0))) | O7: =SUM(C7:N7)
B8: ＋現物出資 追加分 | C8: =IF('②前提'!$C$24=1,'②前提'!$C$22,0) | D8: =IF('②前提'!$C$24=2,'②前提'!$C$22,0) | E8: =IF('②前提'!$C$24=3,'②前提'!$C$22,0) | F8: =IF('②前提'!$C$24=4,'②前提'!$C$22,0) | G8: =IF('②前提'!$C$24=5,'②前提'!$C$22,0) | H8: =IF('②前提'!$C$24=6,'②前提'!$C$22,0) | I8: =IF('②前提'!$C$24=7,'②前提'!$C$22,0) | J8: =IF('②前提'!$C$24=8,'②前提'!$C$22,0) | K8: =IF('②前提'!$C$24=9,'②前提'!$C$22,0) | L8: =IF('②前提'!$C$24=10,'②前提'!$C$22,0) | M8: =IF('②前提'!$C$24=11,'②前提'!$C$22,0) | N8: =IF('②前提'!$C$24=12,'②前提'!$C$22,0) | O8: =SUM(C8:N8)
B9: 売上高 合計 | C9: =SUM(C6:C8) | D9: =SUM(D6:D8) | E9: =SUM(E6:E8) | F9: =SUM(F6:F8) | G9: =SUM(G6:G8) | H9: =SUM(H6:H8) | I9: =SUM(I6:I8) | J9: =SUM(J6:J8) | ... N9: =SUM(N6:N8) | O9: =SUM(C9:N9)
B10: 【売上総利益】
B11: 既存事業 粗利（横ばい分） | C11: ='②前提'!$C$7 | D11: ='②前提'!$C$7 | E11: ='②前提'!$C$7 | F11: ='②前提'!$C$7 | G11: ='②前提'!$C$7 | H11: ='②前提'!$C$7 | I11: ='②前提'!$C$7 | J11: ='②前提'!$C$7 | ... N11: ='②前提'!$C$7 | O11: =SUM(C11:N11)
B12: ＋差額売上の粗利 | C12: ='②前提'!$C$30*'②前提'!$C$31/12 | D12: ='②前提'!$C$30*'②前提'!$C$31/12 | E12: ='②前提'!$C$30*'②前提'!$C$31/12 | F12: ='②前提'!$C$30*'②前提'!$C$31/12 | G12: ='②前提'!$C$30*'②前提'!$C$31/12 | H12: ='②前提'!$C$30*'②前提'!$C$31/12 | I12: ='②前提'!$C$30*'②前提'!$C$31/12 | J12: ='②前提'!$C$30*'②前提'!$C$31/12 | ... N12: ='②前提'!$C$30*'②前提'!$C$31/12 | O12: =SUM(C12:N12)
B13: ＋上乗せ案件（原価なし） | C13: =C7 | D13: =D7 | E13: =E7 | F13: =F7 | G13: =G7 | H13: =H7 | I13: =I7 | J13: =J7 | ... N13: =N7 | O13: =SUM(C13:N13)
B14: ＋現物出資 追加粗利 | C14: =IF('②前提'!$C$24=1,'②前提'!$C$23,0) | D14: =IF('②前提'!$C$24=2,'②前提'!$C$23,0) | E14: =IF('②前提'!$C$24=3,'②前提'!$C$23,0) | F14: =IF('②前提'!$C$24=4,'②前提'!$C$23,0) | G14: =IF('②前提'!$C$24=5,'②前提'!$C$23,0) | H14: =IF('②前提'!$C$24=6,'②前提'!$C$23,0) | I14: =IF('②前提'!$C$24=7,'②前提'!$C$23,0) | J14: =IF('②前提'!$C$24=8,'②前提'!$C$23,0) | K14: =IF('②前提'!$C$24=9,'②前提'!$C$23,0) | L14: =IF('②前提'!$C$24=10,'②前提'!$C$23,0) | M14: =IF('②前提'!$C$24=11,'②前提'!$C$23,0) | N14: =IF('②前提'!$C$24=12,'②前提'!$C$23,0) | O14: =SUM(C14:N14)
B15: 売上総利益 合計 | C15: =SUM(C11:C14) | D15: =SUM(D11:D14) | E15: =SUM(E11:E14) | F15: =SUM(F11:F14) | G15: =SUM(G11:G14) | H15: =SUM(H11:H14) | I15: =SUM(I11:I14) | J15: =SUM(J11:J14) | ... N15: =SUM(N11:N14) | O15: =SUM(C15:N15)
B16: （参考）売上原価 | C16: =C9-C15 | D16: =D9-D15 | E16: =E9-E15 | F16: =F9-F15 | G16: =G9-G15 | H16: =H9-H15 | I16: =I9-I15 | J16: =J9-J15 | ... N16: =N9-N15 | O16: =SUM(C16:N16)
B17: 【販管費・損益】
B18: 販管費 | C18: ='②前提'!$C$8 | D18: ='②前提'!$C$8 | E18: ='②前提'!$C$8 | F18: ='②前提'!$C$8 | G18: ='②前提'!$C$8 | H18: ='②前提'!$C$8 | I18: ='②前提'!$C$8 | J18: ='②前提'!$C$8 | ... N18: ='②前提'!$C$8 | O18: =SUM(C18:N18)
B19: 営業利益 | C19: =C15-C18 | D19: =D15-D18 | E19: =E15-E18 | F19: =F15-F18 | G19: =G15-G18 | H19: =H15-H18 | I19: =I15-I18 | J19: =J15-J18 | ... N19: =N15-N18 | O19: =SUM(C19:N19)
B20: 営業外費用 | C20: ='②前提'!$C$35/12 | D20: ='②前提'!$C$35/12 | E20: ='②前提'!$C$35/12 | F20: ='②前提'!$C$35/12 | G20: ='②前提'!$C$35/12 | H20: ='②前提'!$C$35/12 | I20: ='②前提'!$C$35/12 | J20: ='②前提'!$C$35/12 | ... N20: ='②前提'!$C$35/12 | O20: =SUM(C20:N20)
B21: 経常利益 | C21: =C19-C20 | D21: =D19-D20 | E21: =E19-E20 | F21: =F19-F20 | G21: =G19-G20 | H21: =H19-H20 | I21: =I19-I20 | J21: =J19-J20 | ... N21: =N19-N20 | O21: =SUM(C21:N21)
B23: 営業利益 累計 | C23: =C19 | D23: =C23+D19 | E23: =D23+E19 | F23: =E23+F19 | G23: =F23+G19 | H23: =G23+H19 | I23: =H23+I19 | J23: =I23+J19 | K23: =J23+K19 | ... N23: =M23+N19
B24: 経常利益 累計 | C24: =C21 | D24: =C24+D21 | E24: =D24+E21 | F24: =E24+F21 | G24: =F24+G21 | H24: =G24+H21 | I24: =H24+I21 | J24: =I24+J21 | K24: =J24+K21 | ... N24: =M24+N21
B26: ※既存事業の売上は前期・今期の売上平均を12か月で均等按分。季節変動は織り込んでいません。
B27: ※差額売上の粗利は、横ばい実力値から売上平均までの差額164.2百万円に粗利率30%を乗じたもの。
B28: ※上乗せ案件は原価なし。アピシウスM&A仲介20.0とコンサルティング料10.0はFY2026に前倒し計上済みです。
B29: ※現物出資の追加計上は、②前提で売上0・粗利15.0百万円としています（FY2026と同じ建て付け）。

Sheet ④仕入・在庫計画
B1: ワイン仕入・在庫計画（FY2027）
B2: 期首在庫が187.4百万円まで下がるため、売上を作るには仕入が必要です。単位：円
B4: 【1】在庫の推移
B5: 項目 | C5: プランD | D5: プランE
B6: 期首在庫（2026/09末） | C6: ='②前提'!$C$39 | D6: ='②前提'!$C$39 | E6: FY2026着地予想より
B7: ＋ 年間仕入 | C7: ='②前提'!$C$40 | D7: ='②前提'!$C$40 | E7: ②前提の入力値。割当維持のため落とさない前提
B8: − 売上原価（出庫） | C8: =-('①サマリー'!D8-'①サマリー'!D9) | D8: =-('①サマリー'!E8-'①サマリー'!E9) | E8: 売上高−売上総利益。上乗せ案件・現物出資は原価なし
B9: 期末在庫 | C9: =SUM(C6:C8) | D9: =SUM(D6:D8)
B11: 【2】留意点
B12: ※期首在庫は、2026/09に私募ファンドの売上計上分（原価255百万円）と現物出資分（簿価270百万円）が抜けた後の残高です。
B13: ※プランEは売上原価が589.2百万円に増えるため、仕入450百万円では期末在庫が48.3百万円まで枯渇します。
B14: 上振れを取りにいく場合は仕入も積み増す必要があり、その分の運転資金が追加で要ります。
B15: ※在庫を一定水準（例：期末300百万円）に保つなら、プランDで約491.7百万円、プランEで約701.7百万円の仕入が必要です。
