Workbook

Sheet ①着地予想
B1: FY2026（2026年9月期）着地予想
B2: 2025/10-2026/07は実績、2026/08-09は想定。単位：円（税別）
B4: 【1】営業利益のブリッジ
B5: 項目 | C5: 金額 | D5: 累計 | E5: 内容
B6: 10か月実績 営業利益（2025/10-2026/07） | C6: =SUM('②月次推移表'!C23:L23)+'③前提'!$C$15 | D6: =C6 | E6: 報告値▲111,980,586円に、7月末までの戻し8,000,000円を加算
B7: 8月・9月 既存事業 | C7: =SUM('②月次推移表'!M23:N23)-'③前提'!$C$15-'③前提'!$D$24 | D7: =D6+C7 | E7: 売上115百万円・営業利益トントン（赤字を増やさない）前提のため、貢献はゼロ
B8: 上乗せ4件の粗利 | C8: ='③前提'!$D$24 | D8: =D7+C8 | E8: 私募 現物出資30＋売上計上45＋M&A仲介20＋コンサル料10＝105百万円
B9: FY2026 着地 営業利益 | D9: =D8 | E9: 貴社ご想定の「営業利益0円＋α」と整合します。
B11: 【2】FY2026 着地 損益計算書
B12: 科目 | C12: 10か月実績 | D12: 8月・9月 | E12: 通期 着地
B13: 売上高 | C13: =SUM('②月次推移表'!C11:L11) | D13: =SUM('②月次推移表'!M11:N11) | E13: =C13+D13
B14: 売上原価 | C14: =SUM('②月次推移表'!C16:L16) | D14: =SUM('②月次推移表'!M16:N16) | E14: =C14+D14
B15: 売上総利益 | C15: =SUM('②月次推移表'!C17:L17) | D15: =SUM('②月次推移表'!M17:N17) | E15: =C15+D15
B16: 販管費 計 | C16: =SUM('②月次推移表'!C22:L22) | D16: =SUM('②月次推移表'!M22:N22) | E16: =C16+D16
B17: 営業利益 | C17: =SUM('②月次推移表'!C23:L23) | D17: =SUM('②月次推移表'!M23:N23) | E17: =C17+D17
B18: 営業外収益 | C18: =SUM('②月次推移表'!C24:L24) | D18: =SUM('②月次推移表'!M24:N24) | E18: =C18+D18
B19: 営業外費用 | C19: =SUM('②月次推移表'!C25:L25) | D19: =SUM('②月次推移表'!M25:N25) | E19: =C19+D19
B20: 経常利益 | C20: =SUM('②月次推移表'!C26:L26) | D20: =SUM('②月次推移表'!M26:N26) | E20: =C20+D20
B21: 粗利率 | C21: =C15/C13 | D21: =D15/D13 | E21: =E15/E13
B22: 特別損失（和解金） | E22: 900000
B23: 税引前当期純利益 | E23: =E20-E22
B25: 繰越欠損金 残高（FY2026末 見込） | C25: 127364212 | D25: FY2025分 | E25: =C25+MAX(0,-E23) | F25: FY2027のプランD・Eの法人税計算に使用します。
B27: 【3】留意点
B28: 8-9月の売上レンジは着地に影響しない | C28: 営業利益トントンの前提では、売上が110百万円でも120百万円でも営業利益は変わりません。変わるのは売上高と粗利率の見え方だけです。⑤感応度をご参照ください。
B29: 7月末までの戻し8,000,000円 | C29: 勘定科目（販管費の戻入か売上の追加か）と計上月をご確認ください。本モデルでは販管費の減少として2026年8月に計上しています。
B30: 商品在庫 | C30: 2026/07末の商品は721,162,328円。8-9月の仕入55百万円を見込んでも、私募の売上計上分（原価255百万円）と現物出資分（簿価270百万円）が抜けるため、9月末は約187百万円まで減ります。従来のFY2027モデルの期首在庫420百万円とは大きく異なります。
B31: 消費税 | C31: 課税売上高は890百万円前後です。現物出資分3億円は売上計上しませんが、消費税法上は資産の譲渡等に該当し課税対象となる可能性があります。FY2026分の確定納付額に影響するため、顧問税理士にご確認ください。

Sheet ③前提
B1: FY2026 着地予想 前提条件
B2: 黄色＝入力セル。2025/10-2026/07は実績（添付の損益計算書 月次推移）、2026/08-09は想定。単位：円
B4: 【1】2026年8月・9月の既存事業 ※営業利益トントン（赤字を増やさない）前提
B5: 2026/08 既存事業 売上 | C5: 57500000 | E5: 貴社想定：8-9月の2か月で110〜120百万円。ここでは中央値115百万円を折半
B6: 2026/09 既存事業 売上 | C6: 57500000 | E6: 同上
B7: 2026/08 販管費 | C7: 25624504 | E7: 2026/04-07実績の月平均25,624,504円。貴社ご指定によりフラット
B8: 2026/09 販管費 | C8: 25624504 | E8: 同上
B9: 2026/08 営業外費用 | C9: 1323236 | E9: 2026/04-07実績の月平均
B10: 2026/09 営業外費用 | C10: 1323236 | E10: 同上
B11: ※営業利益トントンの前提により、各月の売上総利益＝販管費として売上原価を逆算しています。
B12: ※この前提では売上レンジ（110〜120百万円）を動かしても着地の営業利益は変わりません。変わるのは売上高と粗利率の見え方だけです。
B14: 【2】7月末までの営業利益の修正（戻し）
B15: 営業利益の戻し | C15: 8000000 | E15: 貴社ご指摘。10か月実績▲111,980,586円に加算し、7月末時点を▲103,980,586円（≒営業赤字10,400万円）とする
B16: 計上月（8＝2026/08・9＝2026/09） | C16: 8 | E16: ★勘定科目（販管費の戻入か売上の追加か）はご確認ください。ここでは販管費の減少として処理しています。
B18: 【3】2026年9月末までに計上する上乗せ案件
B19: 案件 | C19: 売上 | D19: 粗利 | E19: 内容
B20: ① 私募（現物出資分）※売上計上なし | C20: 0 | D20: 30000000 | E20: ★3億円は現物出資のため売上を計上せず、粗利30百万円（P2から10＋WineBankから20）のみ計上。売上原価のマイナスとして処理
B21: ② 私募（売上計上分） | C21: 300000000 | D21: 45000000 | E21: 3億円を売上計上。粗利45百万円（粗利率15.0%）
B22: ③ アピシウスM&A仲介 | C22: 20000000 | D22: 20000000 | E22: FY2027予定分の契約を9月末までに間に合わせる。原価なし
B23: ④ コンサルティング料 | C23: 10000000 | D23: 10000000 | E23: 9月末までに計上。原価なし
B24: 合計 | C24: =SUM(C20:C23) | D24: =SUM(D20:D23) | E24: 粗利105,000,000円は従来想定と同額。売上は630→330百万円に減少（現物出資分3億を売上計上しないため）
B26: 【4】商品在庫の見通し ※FY2027の期首在庫に直結します
B27: 2026/07末 商品（実績） | C27: 721162328 | E27: 添付の貸借対照表 月次推移より
B28: 2026/08-09 商品仕入（想定） | C28: 55000000 | E28: 貴社ご指定：50〜60百万円。中央値55百万円
B29: 2026/08-09 売上原価による出庫 | C29: =SUM('②月次推移表'!M13:N13)+SUM('②月次推移表'!M14:N14) | E29: 既存事業の8-9月＋私募（売上計上分）の原価。現物出資の評価差額は含まない
B30: 現物出資 出資額（評価額） | C30: 300000000 | E30: ★現物出資した金額。売上には計上しません
B31: うち 評価差額（粗利計上分） | C31: =D20 | E31: 【3】①の粗利30,000,000円
B32: 現物出資による在庫の振替（簿価） | C32: =C30-C31 | E32: 出資額−評価差額。売上原価ではなく投資その他の資産へ振替
B33: 2026/09末 商品（見込） | C33: =C27+C28-C29-C32 | E33: 期首＋仕入−出庫−現物出資の振替
B35: ※現物出資したワインは売上原価にはならず、簿価のまま投資その他の資産へ振り替わります。在庫からは出ますが損益には出ません。
B36: ※従来のFY2027モデルは期首在庫420百万円・2026/09に在庫200百万円を販売してみずほ銀行へ返済、という前提でした。
B37: 今回の私募（現物出資300＋売上計上300）はそれより大きい取引のため、期首在庫の前提を置き直す必要があります。

Sheet ②月次推移表
B1: FY2026（2025年10月-2026年9月）月次推移表 実績＋8月・9月想定
B2: 青字＝実績（2025/10-2026/07） 金色斜体＝想定（2026/08-09） 出典：損益計算書 月次推移
B4: 科目 | C4: 2025/10 | D4: 2025/11 | E4: 2025/12 | F4: 2026/01 | G4: 2026/02 | H4: 2026/03 | I4: 2026/04 | J4: 2026/05 | K4: 2026/06 | L4: 2026/07 | M4: 2026/08 | N4: 2026/09 | O4: 通期
B5: 【売上高】
B6: 既存事業 売上 | C6: 32992483 | D6: 97200483 | E6: 43213676 | F6: 32789018 | G6: 41444542 | H6: 33217731 | I6: 32507576 | J6: 35482614 | K6: 32929364 | L6: 63136698 | M6: ='③前提'!$C$5 | N6: ='③前提'!$C$6 | O6: =SUM(C6:N6)
B7: ＋私募（現物出資分）※売上計上なし | C7: 0 | D7: 0 | E7: 0 | F7: 0 | G7: 0 | H7: 0 | I7: 0 | J7: 0 | K7: 0 | L7: 0 | M7: 0 | N7: ='③前提'!$C$20 | O7: =SUM(C7:N7)
B8: ＋私募（売上計上分） | C8: 0 | D8: 0 | E8: 0 | F8: 0 | G8: 0 | H8: 0 | I8: 0 | J8: 0 | K8: 0 | L8: 0 | M8: 0 | N8: ='③前提'!$C$21 | O8: =SUM(C8:N8)
B9: ＋M&A仲介 | C9: 0 | D9: 0 | E9: 0 | F9: 0 | G9: 0 | H9: 0 | I9: 0 | J9: 0 | K9: 0 | L9: 0 | M9: 0 | N9: ='③前提'!$C$22 | O9: =SUM(C9:N9)
B10: ＋コンサルティング料 | C10: 0 | D10: 0 | E10: 0 | F10: 0 | G10: 0 | H10: 0 | I10: 0 | J10: 0 | K10: 0 | L10: 0 | M10: 0 | N10: ='③前提'!$C$23 | O10: =SUM(C10:N10)
B11: 売上高 合計 | C11: =SUM(C6:C10) | D11: =SUM(D6:D10) | E11: =SUM(E6:E10) | F11: =SUM(F6:F10) | G11: =SUM(G6:G10) | H11: =SUM(H6:H10) | I11: =SUM(I6:I10) | J11: =SUM(J6:J10) | ... N11: =SUM(N6:N10) | O11: =SUM(C11:N11)
B12: 【売上原価】
B13: 既存事業 売上原価 | C13: 18502877 | D13: 69212121 | E13: 21085289 | F13: 16521949 | G13: 21070367 | H13: 18454664 | I13: 16184238 | J13: 17021856 | K13: 15172640 | L13: 39686578 | M13: ='③前提'!$C$5-'③前提'!$C$7 | N13: ='③前提'!$C$6-'③前提'!$C$8 | O13: =SUM(C13:N13)
B14: ＋上乗せ案件 原価（売上計上分） | C14: 0 | D14: 0 | E14: 0 | F14: 0 | G14: 0 | H14: 0 | I14: 0 | J14: 0 | K14: 0 | L14: 0 | M14: 0 | N14: =SUM('③前提'!$C$21,'③前提'!$C$22,'③前提'!$C$23)-SUM('③前提'!$D$21,'③前提'!$D$22,'③前提'!$D$23) | O14: =SUM(C14:N14)
B15: ＋現物出資 評価差額（原価のマイナス） | C15: 0 | D15: 0 | E15: 0 | F15: 0 | G15: 0 | H15: 0 | I15: 0 | J15: 0 | K15: 0 | L15: 0 | M15: 0 | N15: =-'③前提'!$D$20 | O15: =SUM(C15:N15)
B16: 売上原価 合計 | C16: =C13+C14+C15 | D16: =D13+D14+D15 | E16: =E13+E14+E15 | F16: =F13+F14+F15 | G16: =G13+G14+G15 | H16: =H13+H14+H15 | I16: =I13+I14+I15 | J16: =J13+J14+J15 | ... N16: =N13+N14+N15 | O16: =SUM(C16:N16)
B17: 売上総利益 | C17: =C11-C16 | D17: =D11-D16 | E17: =E11-E16 | F17: =F11-F16 | G17: =G11-G16 | H17: =H11-H16 | I17: =I11-I16 | J17: =J11-J16 | ... N17: =N11-N16 | O17: =SUM(C17:N17)
B18: 粗利率 | C18: =IF(C11=0,0,C17/C11) | D18: =IF(D11=0,0,D17/D11) | E18: =IF(E11=0,0,E17/E11) | F18: =IF(F11=0,0,F17/F11) | G18: =IF(G11=0,0,G17/G11) | H18: =IF(H11=0,0,H17/H11) | I18: =IF(I11=0,0,I17/I11) | J18: =IF(J11=0,0,J17/J11) | ... N18: =IF(N11=0,0,N17/N11) | O18: =O17/O11
B19: 【販売費及び一般管理費】
B20: 販管費 | C20: 25364892 | D20: 30953282 | E20: 38562456 | F20: 33751779 | G20: 34123901 | H20: 38727868 | I20: 26296530 | J20: 25207614 | K20: 26797697 | L20: 24196173 | M20: ='③前提'!$C$7 | N20: ='③前提'!$C$8 | O20: =SUM(C20:N20)
B21: 7月末までの修正（戻し） | C21: 0 | D21: 0 | E21: 0 | F21: 0 | G21: 0 | H21: 0 | I21: 0 | J21: 0 | K21: 0 | L21: 0 | M21: =-IF('③前提'!$C$16=8,'③前提'!$C$15,0) | N21: =-IF('③前提'!$C$16=9,'③前提'!$C$15,0) | O21: =SUM(C21:N21)
B22: 販管費 計 | C22: =C20+C21 | D22: =D20+D21 | E22: =E20+E21 | F22: =F20+F21 | G22: =G20+G21 | H22: =H20+H21 | I22: =I20+I21 | J22: =J20+J21 | ... N22: =N20+N21 | O22: =SUM(C22:N22)
B23: 営業利益 | C23: =C17-C22 | D23: =D17-D22 | E23: =E17-E22 | F23: =F17-F22 | G23: =G17-G22 | H23: =H17-H22 | I23: =I17-I22 | J23: =J17-J22 | ... N23: =N17-N22 | O23: =SUM(C23:N23)
B24: 営業外収益 | C24: 240000 | D24: 0 | E24: 74699 | F24: 978 | G24: 41468 | H24: 0 | I24: 0 | J24: 0 | K24: 0 | L24: 0 | M24: 0 | N24: 0 | O24: =SUM(C24:N24)
B25: 営業外費用 | C25: 666707 | D25: 638316 | E25: 671047 | F25: 561216 | G25: 1440650 | H25: 1060679 | I25: 1243705 | J25: 989178 | K25: 1686733 | L25: 1373329 | M25: ='③前提'!$C$9 | N25: ='③前提'!$C$10 | O25: =SUM(C25:N25)
B26: 経常利益 | C26: =C23+C24-C25 | D26: =D23+D24-D25 | E26: =E23+E24-E25 | F26: =F23+F24-F25 | G26: =G23+G24-G25 | H26: =H23+H24-H25 | I26: =I23+I24-I25 | J26: =J23+J24-J25 | ... N26: =N23+N24-N25 | O26: =SUM(C26:N26)
B28: 営業利益 累計 | C28: =C23 | D28: =C28+D23 | E28: =D28+E23 | F28: =E28+F23 | G28: =F28+G23 | H28: =G28+H23 | I28: =H28+I23 | J28: =I28+J23 | K28: =J28+K23 | ... N28: =M28+N23
B29: 経常利益 累計 | C29: =C26 | D29: =C29+D26 | E29: =D29+E26 | F29: =E29+F26 | G29: =F29+G26 | H29: =G29+H26 | I29: =H29+I26 | J29: =I29+J26 | K29: =J29+K26 | ... N29: =M29+N26
B31: ※2026/08-09の売上原価は「営業利益トントン」の前提から逆算（売上総利益＝販管費）。
B32: ※上乗せ4件はすべて2026/09に計上。売上330,000,000円・原価225,000,000円・粗利105,000,000円。
B33: ※「7月末までの修正（戻し）」は販管費の減少として2026年8月に計上（貴社ご指定）。
B34: ※私募のうち3億円は現物出資のため売上を計上せず、粗利30,000,000円を売上原価のマイナスとして計上しています。

Sheet ⑤感応度
B1: 8月・9月の既存事業 売上レンジ別の着地
B2: 営業利益トントンの前提のため、売上が変わっても営業利益・経常利益は変わりません。
B4: 【1】売上レンジ別
B5: 8-9月 既存売上 | C5: 通期 売上高 | D5: 通期 粗利率 | E5: 通期 営業利益 | F5: 通期 経常利益
B6: 110000000 | C6: =SUM('②月次推移表'!C11:L11)+B6+'③前提'!$C$20+'③前提'!$C$21+'③前提'!$C$22+'③前提'!$C$23 | D6: =(SUM('②月次推移表'!C17:L17)+'③前提'!$C$7+'③前提'!$C$8+'③前提'!$D$24)/C6 | E6: ='①着地予想'!E17 | F6: ='①着地予想'!E20
B7: 115000000 | C7: =SUM('②月次推移表'!C11:L11)+B7+'③前提'!$C$20+'③前提'!$C$21+'③前提'!$C$22+'③前提'!$C$23 | D7: =(SUM('②月次推移表'!C17:L17)+'③前提'!$C$7+'③前提'!$C$8+'③前提'!$D$24)/C7 | E7: ='①着地予想'!E17 | F7: ='①着地予想'!E20
B8: 120000000 | C8: =SUM('②月次推移表'!C11:L11)+B8+'③前提'!$C$20+'③前提'!$C$21+'③前提'!$C$22+'③前提'!$C$23 | D8: =(SUM('②月次推移表'!C17:L17)+'③前提'!$C$7+'③前提'!$C$8+'③前提'!$D$24)/C8 | E8: ='①着地予想'!E17 | F8: ='①着地予想'!E20
B10: ※中央値115百万円が②月次推移表の設定値です（8月・9月に折半）。
B11: ※営業利益・経常利益が一定なのは、粗利＝販管費とする「トントン」前提の必然です。売上が伸びれば粗利率が下がる形で調整されます。
B12: ※8-9月に営業利益を出せる見込みがあれば、その分だけ着地は上振れします。

Sheet ④添付ファイル検証
B1: 添付ファイル（損益計算書 月次推移 2025/10-2026/07）の検証
B2: 合計欄と月次の積み上げ、各月の内部整合、棚卸高の連続性を確認しました。
B4: 【1】合計欄と月次積み上げの照合
B5: 項目 | C5: 月次の積み上げ | D5: 報告書の合計欄 | E5: 判定
B6: 売上高 | C6: 444914185 | D6: 444914185 | E6: =IF(C6=D6,"一致","差異 "&TEXT(C6-D6,"#,##0"))
B7: 売上原価 | C7: 252912579 | D7: 252912579 | E7: =IF(C7=D7,"一致","差異 "&TEXT(C7-D7,"#,##0"))
B8: 売上総利益 | C8: 192001606 | D8: 192001606 | E8: =IF(C8=D8,"一致","差異 "&TEXT(C8-D8,"#,##0"))
B9: 販管費 | C9: 303982192 | D9: 303982192 | E9: =IF(C9=D9,"一致","差異 "&TEXT(C9-D9,"#,##0"))
B10: 営業利益 | C10: -111980586 | D10: -111980586 | E10: =IF(C10=D10,"一致","差異 "&TEXT(C10-D10,"#,##0"))
B11: 営業外収益 | C11: 357145 | D11: 357145 | E11: =IF(C11=D11,"一致","差異 "&TEXT(C11-D11,"#,##0"))
B12: 営業外費用 | C12: 10331560 | D12: 10331560 | E12: =IF(C12=D12,"一致","差異 "&TEXT(C12-D12,"#,##0"))
B13: 経常利益 | C13: -121955001 | D13: -121955001 | E13: =IF(C13=D13,"一致","差異 "&TEXT(C13-D13,"#,##0"))
B14: 商品仕入高 | C14: 469514545 | D14: 469514545 | E14: =IF(C14=D14,"一致","差異 "&TEXT(C14-D14,"#,##0"))
B15: 賄費戻り金 | C15: -417040 | D15: -417040 | E15: =IF(C15=D15,"一致","差異 "&TEXT(C15-D15,"#,##0"))
B17: 【2】各月の内部整合（全10か月）
B18: 売上総利益 ＝ 売上高 − 売上原価 | C18: 全10か月で一致
B19: 営業利益 ＝ 売上総利益 − 販管費 | C19: 全10か月で一致
B20: 経常利益 ＝ 営業利益 ＋ 営業外収益 − 営業外費用 | C20: 全10か月で一致
B21: 売上原価 ＝ 期首棚卸 ＋ 仕入 ＋ 賄費戻り金 − 期末棚卸 | C21: 全10か月で一致
B22: 売上高 ＝ 内訳7科目の合計 | C22: 全10か月で一致
B23: 税引前 ＝ 経常利益 − 特別損失900,000（和解金） | C23: 一致。特別利益は0
B25: 【3】確認が必要な点 ※棚卸高の連続性
C26: 前月末 棚卸高 | D26: 当月首 棚卸高 | E26: 差異
B27: 2025/10末 → 2025/11首 | C27: 508671841 | D27: 513186113 | E27: 4514272
B28: 2026/02末 → 2026/03首 | C28: 605126013 | D28: 604529401 | E28: -596612
B29: 純額 | E29: 3917660
B31: ※月をまたぐ棚卸高が2か所で一致していません（洗い替えと思われます）。各月の売上原価は月内で整合しているため、
B32: 通期の売上原価252,912,579円は月次の積み上げとしては正しい数値です。
B33: ※一方、期首501,059,742円・期末721,162,328円と仕入469,514,545円から逆算すると売上原価は248,994,919円となり、
B34: 報告値との差3,917,660円は上記2件の純額と完全に一致します。通期の在庫増減を使って検算する際はご注意ください。
B35: ※商品在庫は10か月で501.1百万円→721.2百万円と220.1百万円増えています。FY2027の期首在庫に直結する論点です。
B37: 【4】転記時に判明した点
B38: ※2026/04の売上高を32,501,576円と読むと内訳合計および売上総利益と6,000円ずれます。32,507,576円が正しい数値です。
B39: ※和解金900,000円は特別損失であり、特別利益は0です（税引前当期純利益▲122,855,001円と整合）。
