Workbook

Sheet セグメント集計_含む除く
A1: セグメント別 連結業績（百万円） 営業利益の青字＝2026/10/22 デックp.41での修正値（経営判断）
A3: セグメント | B3: 区分 | C3: 2026年度 2026/10-2027/9 | D3: 2027年度 2027/10-2028/9 | E3: 2028年度 2028/10-2029/9 | F3: 2029年度 2029/10-2030/9
A4: ワイン・WineTech | B4: 売上高 | C4: =連結PL_WineBank年度!C5+連結PL_WineBank年度!C7+連結PL_WineBank年度!C9 -> 750.5 | D4: =連結PL_WineBank年度!D5+連結PL_WineBank年度!D7+連結PL_WineBank年度!D9 -> 1165.4 | E4: =連結PL_WineBank年度!E5+連結PL_WineBank年度!E7+連結PL_WineBank年度!E9 -> 1266.1 | F4: =連結PL_WineBank年度!F5+連結PL_WineBank年度!F7+連結PL_WineBank年度!F9 -> 1376.9
A5: ワイン・WineTech | B5: 営業利益（モデル） | C5: =連結PL_WineBank年度!C6+連結PL_WineBank年度!C8+連結PL_WineBank年度!C10 -> 22.9 | D5: =連結PL_WineBank年度!D6+連結PL_WineBank年度!D8+連結PL_WineBank年度!D10 -> 143.2 | E5: =連結PL_WineBank年度!E6+連結PL_WineBank年度!E8+連結PL_WineBank年度!E10 -> 170.6 | F5: =連結PL_WineBank年度!F6+連結PL_WineBank年度!F8+連結PL_WineBank年度!F10 -> 200.4
A6: ワイン・WineTech | B6: 営業利益 | C6: 10 | D6: 100 | E6: 150 | F6: 200
A7: ワイン・WineTech | B7: 持分按分後 営業利益 | C7: =C6*(連結PL_WineBank年度!C6*入力_各社決算期ベース!C4+連結PL_WineBank年度!C8*入力_各社決算期ベース!C5+連結PL_WineBank年度!C10*入力_各社決算期ベース!C6)/C5 -> 10 | D7: =D6*(連結PL_WineBank年度!D6*入力_各社決算期ベース!C4+連結PL_WineBank年度!D8*入力_各社決算期ベース!C5+連結PL_WineBank年度!D10*入力_各社決算期ベース!C6)/D5 -> 100 | E7: =E6*(連結PL_WineBank年度!E6*入力_各社決算期ベース!C4+連結PL_WineBank年度!E8*入力_各社決算期ベース!C5+連結PL_WineBank年度!E10*入力_各社決算期ベース!C6)/E5 -> 150 | F7: =F6*(連結PL_WineBank年度!F6*入力_各社決算期ベース!C4+連結PL_WineBank年度!F8*入力_各社決算期ベース!C5+連結PL_WineBank年度!F10*入力_各社決算期ベース!C6)/F5 -> 200
A8: グランメゾン | B8: 売上高 | C8: =連結PL_WineBank年度!C11+連結PL_WineBank年度!C13 -> 1766 | D8: =連結PL_WineBank年度!D11+連結PL_WineBank年度!D13 -> 1823.95 | E8: =連結PL_WineBank年度!E11+連結PL_WineBank年度!E13 -> 1879.825 | F8: =連結PL_WineBank年度!F11+連結PL_WineBank年度!F13 -> 1941.75
A9: グランメゾン | B9: 営業利益（モデル） | C9: =連結PL_WineBank年度!C12+連結PL_WineBank年度!C14 -> 682.075 | D9: =連結PL_WineBank年度!D12+連結PL_WineBank年度!D14 -> 708.1 | E9: =連結PL_WineBank年度!E12+連結PL_WineBank年度!E14 -> 733.675 | F9: =連結PL_WineBank年度!F12+連結PL_WineBank年度!F14 -> 762.4
A10: グランメゾン | B10: 営業利益 | C10: =C9 -> 682.075 | D10: =D9 -> 708.1 | E10: =E9 -> 733.675 | F10: =F9 -> 762.4
A11: グランメゾン | B11: 持分按分後 営業利益 | C11: =C10*(連結PL_WineBank年度!C12*入力_各社決算期ベース!C7+連結PL_WineBank年度!C14*入力_各社決算期ベース!C8)/C9 -> 373.1425 | D11: =D10*(連結PL_WineBank年度!D12*入力_各社決算期ベース!C7+連結PL_WineBank年度!D14*入力_各社決算期ベース!C8)/D9 -> 387.18 | E11: =E10*(連結PL_WineBank年度!E12*入力_各社決算期ベース!C7+連結PL_WineBank年度!E14*入力_各社決算期ベース!C8)/E9 -> 400.9975 | F11: =F10*(連結PL_WineBank年度!F12*入力_各社決算期ベース!C7+連結PL_WineBank年度!F14*入力_各社決算期ベース!C8)/F9 -> 416.45475
A12: ブラッスリー | B12: 売上高 | C12: =連結PL_WineBank年度!C15 -> 190.5 | D12: =連結PL_WineBank年度!D15 -> 636.1 | E12: =連結PL_WineBank年度!E15 -> 1310.3 | F12: =連結PL_WineBank年度!F15 -> 2152.75
A13: ブラッスリー | B13: 営業利益（モデル） | C13: =連結PL_WineBank年度!C16 -> 5.15 | D13: =連結PL_WineBank年度!D16 -> 24.7 | E13: =連結PL_WineBank年度!E16 -> 72.45 | F13: =連結PL_WineBank年度!F16 -> 144.9
A14: ブラッスリー | B14: 営業利益 | C14: =C13 -> 5.15 | D14: =D13 -> 24.7 | E14: =E13 -> 72.45 | F14: =F13 -> 144.9
A15: ブラッスリー | B15: 持分按分後 営業利益 | C15: =C14*(連結PL_WineBank年度!C16*入力_各社決算期ベース!C9)/C13 -> 3.43505 | D15: =D14*(連結PL_WineBank年度!D16*入力_各社決算期ベース!C9)/D13 -> 16.4749 | E15: =E14*(連結PL_WineBank年度!E16*入力_各社決算期ベース!C9)/E13 -> 48.32415 | F15: =F14*(連結PL_WineBank年度!F16*入力_各社決算期ベース!C9)/F13 -> 96.6483
A16: レストラン運営 | B16: 売上高 | C16: =連結PL_WineBank年度!C17+連結PL_WineBank年度!C19 -> 1505.25 | D16: =連結PL_WineBank年度!D17+連結PL_WineBank年度!D19 -> 1526.4 | E16: =連結PL_WineBank年度!E17+連結PL_WineBank年度!E19 -> 1548.175 | F16: =連結PL_WineBank年度!F17+連結PL_WineBank年度!F19 -> 1570.65
A17: レストラン運営 | B17: 営業利益（モデル） | C17: =連結PL_WineBank年度!C18+連結PL_WineBank年度!C20 -> 130.75 | D17: =連結PL_WineBank年度!D18+連結PL_WineBank年度!D20 -> 133.775 | E17: =連結PL_WineBank年度!E18+連結PL_WineBank年度!E20 -> 136.9 | F17: =連結PL_WineBank年度!F18+連結PL_WineBank年度!F20 -> 140.125
A18: レストラン運営 | B18: 営業利益 | C18: 130 | D18: 100 | E18: 100 | F18: 100
A19: レストラン運営 | B19: 持分按分後 営業利益 | C19: =C18*(連結PL_WineBank年度!C18*入力_各社決算期ベース!C10+連結PL_WineBank年度!C20*入力_各社決算期ベース!C11)/C17 -> 80.982792 | D19: =D18*(連結PL_WineBank年度!D18*入力_各社決算期ベース!C10+連結PL_WineBank年度!D20*入力_各社決算期ベース!C11)/D17 -> 62.242571 | E19: =E18*(連結PL_WineBank年度!E18*入力_各社決算期ベース!C10+連結PL_WineBank年度!E20*入力_各社決算期ベース!C11)/E17 -> 62.191381 | F19: =F18*(連結PL_WineBank年度!F18*入力_各社決算期ベース!C10+連結PL_WineBank年度!F20*入力_各社決算期ベース!C11)/F17 -> 62.140946
A20: 連結売上高（カンテサンス含む） | C20: =C4+C8+C12+C16 -> 4212.25 | D20: =D4+D8+D12+D16 -> 5151.85 | E20: =E4+E8+E12+E16 -> 6004.4 | F20: =F4+F8+F12+F16 -> 7042.05
A21: 連結営業利益（カンテサンス含む） | C21: =C6+C10+C14+C18 -> 827.225 | D21: =D6+D10+D14+D18 -> 932.8 | E21: =E6+E10+E14+E18 -> 1056.125 | F21: =F6+F10+F14+F18 -> 1207.3
A22: 持分按分後 営業利益（カンテサンス含む） | C22: =C7+C11+C15+C19 -> 467.56034 | D22: =D7+D11+D15+D19 -> 565.89747 | E22: =E7+E11+E15+E19 -> 661.51303 | F22: =F7+F11+F15+F19 -> 775.244
A23: 連結売上高（カンテサンス除く） | C23: =C20-連結PL_WineBank年度!C13 -> 3162 | D23: =D20-連結PL_WineBank年度!D13 -> 4065.1 | E23: =E20-連結PL_WineBank年度!E13 -> 4883.9 | F23: =F20-連結PL_WineBank年度!F13 -> 5882.45
A24: 連結営業利益（カンテサンス除く） | C24: =C21-連結PL_WineBank年度!C14 -> 278.225 | D24: =D21-連結PL_WineBank年度!D14 -> 361.8 | E24: =E21-連結PL_WineBank年度!E14 -> 463.625 | F24: =F21-連結PL_WineBank年度!F14 -> 590.325
A25: 持分按分後 営業利益（カンテサンス除く） | C25: =C22-連結PL_WineBank年度!C14*入力_各社決算期ベース!C8 -> 187.57034 | D25: =D22-連結PL_WineBank年度!D14*入力_各社決算期ベース!C8 -> 274.68747 | E25: =E22-連結PL_WineBank年度!E14*入力_各社決算期ベース!C8 -> 359.33803 | F25: =F22-連結PL_WineBank年度!F14*入力_各社決算期ベース!C8 -> 460.58675

Sheet 連結PL_WineBank年度
A1: 組織再編後 連結損益計画（百万円） 年度＝WineBank決算期（10月〜翌9月）
A2: 決算期が異なる子会社は月数按分で組替え。グループ内取引の消去は未反映（WineBank側のグループ内コンサル料は消去済）
A4: 事業 | B4: 区分 | C4: 2026年度 2026/10-2027/9 | D4: 2027年度 2027/10-2028/9 | E4: 2028年度 2028/10-2029/9 | F4: 2029年度 2029/10-2030/9
A5: WineBank 既存ワイン事業 | B5: 売上高 | C5: =入力_各社決算期ベース!E4*12/12 -> 750.5 | D5: =入力_各社決算期ベース!F4*12/12 -> 788 | E5: =入力_各社決算期ベース!G4*12/12 -> 827.4 | F5: =入力_各社決算期ベース!H4*12/12 -> 868.8
A6: WineBank 既存ワイン事業 | B6: 営業利益 | C6: =入力_各社決算期ベース!K4*12/12 -> 22.9 | D6: =入力_各社決算期ベース!L4*12/12 -> 34.2 | E6: =入力_各社決算期ベース!M4*12/12 -> 46 | F6: =入力_各社決算期ベース!N4*12/12 -> 58.4
A7: WineBank 私募ファンド・オークション | B7: 売上高 | C7: =入力_各社決算期ベース!E5*12/12 -> 0 | D7: =入力_各社決算期ベース!F5*12/12 -> 300 | E7: =入力_各社決算期ベース!G5*12/12 -> 300 | F7: =入力_各社決算期ベース!H5*12/12 -> 300
A8: WineBank 私募ファンド・オークション | B8: 営業利益 | C8: =入力_各社決算期ベース!K5*12/12 -> 0 | D8: =入力_各社決算期ベース!L5*12/12 -> 90 | E8: =入力_各社決算期ベース!M5*12/12 -> 90 | F8: =入力_各社決算期ベース!N5*12/12 -> 90
A9: WineBank ワインマイル | B9: 売上高 | C9: =入力_各社決算期ベース!E6*12/12 -> 0 | D9: =入力_各社決算期ベース!F6*12/12 -> 77.4 | E9: =入力_各社決算期ベース!G6*12/12 -> 138.7 | F9: =入力_各社決算期ベース!H6*12/12 -> 208.1
A10: WineBank ワインマイル | B10: 営業利益 | C10: =入力_各社決算期ベース!K6*12/12 -> 0 | D10: =入力_各社決算期ベース!L6*12/12 -> 19 | E10: =入力_各社決算期ベース!M6*12/12 -> 34.6 | F10: =入力_各社決算期ベース!N6*12/12 -> 52
A11: アピシウス | B11: 売上高 | C11: =入力_各社決算期ベース!D7*3/12+入力_各社決算期ベース!E7*9/12 -> 715.75 | D11: =入力_各社決算期ベース!E7*3/12+入力_各社決算期ベース!F7*9/12 -> 737.2 | E11: =入力_各社決算期ベース!F7*3/12+入力_各社決算期ベース!G7*9/12 -> 759.325 | F11: =入力_各社決算期ベース!G7*3/12+入力_各社決算期ベース!H7*9/12 -> 782.15
A12: アピシウス | B12: 営業利益 | C12: =入力_各社決算期ベース!J7*3/12+入力_各社決算期ベース!K7*9/12 -> 133.075 | D12: =入力_各社決算期ベース!K7*3/12+入力_各社決算期ベース!L7*9/12 -> 137.1 | E12: =入力_各社決算期ベース!L7*3/12+入力_各社決算期ベース!M7*9/12 -> 141.175 | F12: =入力_各社決算期ベース!M7*3/12+入力_各社決算期ベース!N7*9/12 -> 145.425
A13: カンテサンス（プティ・ボノム） | B13: 売上高 | C13: =入力_各社決算期ベース!D8*3/12+入力_各社決算期ベース!E8*9/12 -> 1050.25 | D13: =入力_各社決算期ベース!E8*3/12+入力_各社決算期ベース!F8*9/12 -> 1086.75 | E13: =入力_各社決算期ベース!F8*3/12+入力_各社決算期ベース!G8*9/12 -> 1120.5 | F13: =入力_各社決算期ベース!G8*3/12+入力_各社決算期ベース!H8*9/12 -> 1159.6
A14: カンテサンス（プティ・ボノム） | B14: 営業利益 | C14: =入力_各社決算期ベース!J8*3/12+入力_各社決算期ベース!K8*9/12 -> 549 | D14: =入力_各社決算期ベース!K8*3/12+入力_各社決算期ベース!L8*9/12 -> 571 | E14: =入力_各社決算期ベース!L8*3/12+入力_各社決算期ベース!M8*9/12 -> 592.5 | F14: =入力_各社決算期ベース!M8*3/12+入力_各社決算期ベース!N8*9/12 -> 616.975
A15: Brasserie Thierry Marx | B15: 売上高 | C15: =入力_各社決算期ベース!E9*6/12+入力_各社決算期ベース!F9*6/12 -> 190.5 | D15: =入力_各社決算期ベース!F9*6/12+入力_各社決算期ベース!G9*6/12 -> 636.1 | E15: =入力_各社決算期ベース!G9*6/12+入力_各社決算期ベース!H9*6/12 -> 1310.3 | F15: =入力_各社決算期ベース!H9*6/12+入力_各社決算期ベース!I9*6/12 -> 2152.75
A16: Brasserie Thierry Marx | B16: 営業利益 | C16: =入力_各社決算期ベース!K9*6/12+入力_各社決算期ベース!L9*6/12 -> 5.15 | D16: =入力_各社決算期ベース!L9*6/12+入力_各社決算期ベース!M9*6/12 -> 24.7 | E16: =入力_各社決算期ベース!M9*6/12+入力_各社決算期ベース!N9*6/12 -> 72.45 | F16: =入力_各社決算期ベース!N9*6/12+入力_各社決算期ベース!O9*6/12 -> 144.9
A17: バリューキッチン | B17: 売上高 | C17: =入力_各社決算期ベース!E10*9/12+入力_各社決算期ベース!F10*3/12 -> 705.25 | D17: =入力_各社決算期ベース!F10*9/12+入力_各社決算期ベース!G10*3/12 -> 726.4 | E17: =入力_各社決算期ベース!G10*9/12+入力_各社決算期ベース!H10*3/12 -> 748.175 | F17: =入力_各社決算期ベース!H10*9/12+入力_各社決算期ベース!I10*3/12 -> 770.65
A18: バリューキッチン | B18: 営業利益 | C18: =入力_各社決算期ベース!K10*9/12+入力_各社決算期ベース!L10*3/12 -> 100.75 | D18: =入力_各社決算期ベース!L10*9/12+入力_各社決算期ベース!M10*3/12 -> 103.775 | E18: =入力_各社決算期ベース!M10*9/12+入力_各社決算期ベース!N10*3/12 -> 106.9 | F18: =入力_各社決算期ベース!N10*9/12+入力_各社決算期ベース!O10*3/12 -> 110.125
A19: その他グループ会社（バリューテーブル・エルネット等） | B19: 売上高 | C19: =入力_各社決算期ベース!E11*12/12 -> 800 | D19: =入力_各社決算期ベース!F11*12/12 -> 800 | E19: =入力_各社決算期ベース!G11*12/12 -> 800 | F19: =入力_各社決算期ベース!H11*12/12 -> 800
A20: その他グループ会社（バリューテーブル・エルネット等） | B20: 営業利益 | C20: =入力_各社決算期ベース!K11*12/12 -> 30 | D20: =入力_各社決算期ベース!L11*12/12 -> 30 | E20: =入力_各社決算期ベース!M11*12/12 -> 30 | F20: =入力_各社決算期ベース!N11*12/12 -> 30
A21: 連結売上高 | C21: =C5+C7+C9+C11+C13+C15+C17+C19 -> 4212.25 | D21: =D5+D7+D9+D11+D13+D15+D17+D19 -> 5151.85 | E21: =E5+E7+E9+E11+E13+E15+E17+E19 -> 6004.4 | F21: =F5+F7+F9+F11+F13+F15+F17+F19 -> 7042.05
A22: 連結営業利益（モデル値・p.41修正前） | C22: =C6+C8+C10+C12+C14+C16+C18+C20 -> 840.875 | D22: =D6+D8+D10+D12+D14+D16+D18+D20 -> 1009.775 | E22: =E6+E8+E10+E12+E14+E16+E18+E20 -> 1113.625 | F22: =F6+F8+F10+F12+F14+F16+F18+F20 -> 1247.825
A23: 営業利益率 | C23: =C22/C21 -> 0.19962609 | D23: =D22/D21 -> 0.19600241 | E23: =E22/E21 -> 0.18546816 | F23: =F22/F21 -> 0.17719627
A24: （参考）持分按分後 営業利益（モデル値・修正前） | B24: 親会社帰属の目安 | C24: =C6*入力_各社決算期ベース!C4+C8*入力_各社決算期ベース!C5+C10*入力_各社決算期ベース!C6+C12*入力_各社決算期ベース!C7+C14*入力_各社決算期ベース!C8+C16*入力_各社決算期ベース!C9+C18*入力_各社決算期ベース!C10+C20*入力_各社決算期ベース!C11 -> 480.92755 | D24: =D6*入力_各社決算期ベース!C4+D8*入力_各社決算期ベース!C5+D10*入力_各社決算期ベース!C6+D12*入力_各社決算期ベース!C7+D14*入力_各社決算期ベース!C8+D16*入力_各社決算期ベース!C9+D18*入力_各社決算期ベース!C10+D20*入力_各社決算期ベース!C11 -> 630.1199 | E24: =E6*入力_各社決算期ベース!C4+E8*入力_各社決算期ベース!C5+E10*入力_各社決算期ベース!C6+E12*入力_各社決算期ベース!C7+E14*入力_各社決算期ベース!C8+E16*入力_各社決算期ベース!C9+E18*入力_各社決算期ベース!C10+E20*入力_各社決算期ベース!C11 -> 705.06165 | F24: =F6*入力_各社決算期ベース!C4+F8*入力_各社決算期ベース!C5+F10*入力_各社決算期ベース!C6+F12*入力_各社決算期ベース!C7+F14*入力_各社決算期ベース!C8+F16*入力_各社決算期ベース!C9+F18*入力_各社決算期ベース!C10+F20*入力_各社決算期ベース!C11 -> 800.57805

Sheet 入力_各社決算期ベース
A1: 各社の自社決算期ベースの計画（百万円） 青字＝入力値
A3: 事業 | B3: 決算月 | C3: WineBank持分 | D3: 2026年 売上 | E3: 2027年 売上 | F3: 2028年 売上 | G3: 2029年 売上 | H3: 2030年 売上 | I3: 2031年 売上 | J3: 2026年 営業利益 | K3: 2027年 営業利益 | L3: 2028年 営業利益 | M3: 2029年 営業利益 | N3: 2030年 営業利益 | O3: 2031年 営業利益 | P3: 出所・前提
A4: WineBank 既存ワイン事業 | B4: 9 | C4: 1 | E4: 750.5 | F4: 788 | G4: 827.4 | H4: 868.8 | K4: 22.9 | L4: 34.2 | M4: 46 | N4: 58.4 | P4: 2026年度＝銀行提出 FY2027プランD（売上833.0・営業利益105.4）からグループ内コンサル料82.5を消去。2027年度以降は年5%成長・増分粗利率30%・販管費据置の仮置き
A5: WineBank 私募ファンド・オークション | B5: 9 | C5: 1 | E5: 0 | F5: 300 | G5: 300 | H5: 300 | K5: 0 | L5: 90 | M5: 90 | N5: 90 | P5: 銀行提出 FY2027プランE（上振れ）の上積み300（粗利率30%）を2027年度から据置で計上
A6: WineBank ワインマイル | B6: 9 | C6: 1 | E6: 0 | F6: 77.4 | G6: 138.7 | H6: 208.1 | K6: 0 | L6: 19 | M6: 34.6 | N6: 52 | P6: ワインマイル3か年PL（9/2版）を最新レートカード（管理料2.75%・還元率4/5/6%・成功報酬30%・GOLD500万〜、9/29）で再計算した1〜3年目。2027年度を1年目とし、人件費・システム費は既存体制で吸収
A7: アピシウス | B7: 12 | C7: 0.7 | D7: 700 | E7: 721 | F7: 742.6 | G7: 764.9 | H7: 787.9 | J7: 130 | K7: 134.1 | L7: 138.1 | M7: 142.2 | N7: 146.5 | P7: 2026年12月期＝グループ管理表の着地予想。2027年以降は売上年3%成長・営業利益率18.6%据置の仮置き
A8: カンテサンス（プティ・ボノム） | B8: 12 | C8: 0.51 | D8: 1015 | E8: 1062 | F8: 1095 | G8: 1129 | H8: 1169.8 | J8: 528 | K8: 556 | L8: 576 | M8: 598 | N8: 623.3 | P8: IM（2026年9月）42頁 監修後・売上横ばいケース。2030年はIMの年平均成長率で延長（CF計画2027-2032）。岸田氏報酬見直し等の取得後改善（年約0.8億）と一時費用（役員退職金2.25億）は含めない
A9: Brasserie Thierry Marx | B9: 3 | C9: 0.667 | E9: 0 | F9: 381 | G9: 891.2 | H9: 1729.4 | I9: 2576.1 | K9: 0 | L9: 10.3 | M9: 39.1 | N9: 105.8 | O9: 184 | P9: 事業収支統合モデル 2026/10/16 v4 連結PL（FY＝4月〜3月）。2027年3月期は開業前のため0
A10: バリューキッチン | B10: 6 | C10: 0.6 | E10: 700 | F10: 721 | G10: 742.6 | H10: 764.9 | I10: 787.9 | K10: 100 | L10: 103 | M10: 106.1 | N10: 109.3 | O10: 112.6 | P10: グループ管理表の着地予想（売上700・営業利益100）を2027年6月期に充当（2026年6月期実績：売上645・店舗営業利益75）。以降は年3%成長の仮置き
A11: その他グループ会社（バリューテーブル・エルネット等） | B11: 9 | C11: 0.7 | E11: 800 | F11: 800 | G11: 800 | H11: 800 | K11: 30 | L11: 30 | M11: 30 | N11: 30 | P11: グループ管理表の着地予想：バリューテーブル600/20・エルネット100/5・摩耶100/5の合計を据置
A13: 対象外：あどばる（37%・ビジョングループ）、KINKA（20%）、バーガーレボリューション（49%）は持分法または対象外。ワイン・ラ・ターブルは店舗をバリューキッチンへ移管済のため除外
A14: WineBank持分：再編後の想定。カンテサンスはSPCでWineBank・アピシウス50〜66.7%（下限50%で記載）、Brasserie Thierry Marxは外部投資家33.3%、その他はグループ管理表の保有比率
