Workbook

Sheet 前提
A1: カンテサンス 2027年 月次キャッシュフロー計画 ― 前提条件
A2: 単位：百万円。青字＝入力値、黒字＝計算式、黄色＝感応度を見るための主要レバー。
A4: 1. 損益前提（2026年12月期の会社計画と同水準で横ばい）
A5: 売上高（年間） | B5: 1015 | D5: IM p.40 の2026年12月期 会社計画
A6: 営業利益（年間） | B6: 528 | D6: 同上。役員報酬・賞与を控除した後の金額
A7: 変動費率（食材・ドリンク原価） | B7: 0.254 | D7: ドリンク原価0.9万円/人×1.4万人＋食材原価から逆算
A8: 月次固定費 | B8: =(B5*(1-B7)-B6)/12 -> 19.099167 | D8: ＝（売上高×(1−変動費率)−営業利益）÷12。人件費・役員報酬・賃料等
A10: 2. 月次の営業日数（年間252日）
A11: 月 | B11: 1月 | C11: 2月 | D11: 3月 | E11: 4月 | F11: 5月 | G11: 6月 | H11: 7月 | I11: 8月 | J11: 9月 | K11: 10月 | L11: 11月 | M11: 12月 | N11: 合計
A12: 営業日数 | B12: 18 | C12: 20 | D12: 22 | E12: 21 | F12: 21 | G12: 22 | H12: 22 | I12: 17 | J12: 21 | K12: 22 | L12: 21 | M12: 25 | N12: =SUM(B12:M12) -> 252
A13: ※ 1月は年始休業、8月は夏季休業、12月は繁忙期のため営業日数を増やす前提。月次売上は営業日数に比例させている。
A15: 3. 税金
A16: 2026年12月期の未払法人税等・未払消費税（2027年2月納付） | B16: 114 | D16: 2026年12月期末BSの負債に計上されている金額。取得後の会社が納付する
A17: 法人税等 2027年度 中間納付（2027年8月） | B17: 92 | D17: 前事業年度の確定法人税額の2分の1
A18: （期中の消費税） | B18: 0 | D18: 売上高は税抜表示であり、消費税は預り金の性質を持つ。顧客からの預りと税務署への納付が年間を通じて相殺されるため、本モデルでは計上していない
A19: ※ 2026年12月期の未払税金は、譲受価額の算定において控除していない（事業価値の算定は現預金と役員貸付金のみを非事業用資産として扱っている）。 ※ 合併に伴う資産調整勘定（税務上ののれん）の損金算入は、保守的に織り込んでいない。認められる場合、2027年度の法人税はほぼ発生しない。
A21: 4. 買収ファイナンスと期首現金
A22: 有利子負債（2027年1月1日、ブリッジ返済後） | B22: 2000 | D22: タームローンA 14.0億円＋タームローンB 6.0億円
A23: 金利 | B23: 0.03 | D23: みずほ銀行との協議前提
A24: 四半期の元本返済額 | B24: 50 | D24: タームローンA 14.0億円を7年元金均等＝年2.0億円。3月・6月・9月・12月に返済
A25: 期首現金（対象会社に留保する運転資金） | B25: 100 | D25: ★ 本モデルの主要レバー。ここを増減させると買収時に必要な中野氏の拠出額が同額だけ変動する

Sheet 月次CF
A1: 2027年 月次キャッシュフロー計画（百万円）
A2: 計画どおり（2026年12月期の会社計画と同水準）に推移した場合。すべて『前提』シートを参照している。
A3: 2027年 | B3: 1月 | C3: 2月 | D3: 3月 | E3: 4月 | F3: 5月 | G3: 6月 | H3: 7月 | I3: 8月 | J3: 9月 | K3: 10月 | L3: 11月 | M3: 12月 | N3: 合計
A4: 月番号 | B4: 1 | C4: 2 | D4: 3 | E4: 4 | F4: 5 | G4: 6 | H4: 7 | I4: 8 | J4: 9 | K4: 10 | L4: 11 | M4: 12
A5: 月 | B5: 1月 | C5: 2月 | D5: 3月 | E5: 4月 | F5: 5月 | G5: 6月 | H5: 7月 | I5: 8月 | J5: 9月 | K5: 10月 | L5: 11月 | M5: 12月
A6: 営業日数 | B6: =前提!B12 -> 18 | C6: =前提!C12 -> 20 | D6: =前提!D12 -> 22 | E6: =前提!E12 -> 21 | F6: =前提!F12 -> 21 | G6: =前提!G12 -> 22 | H6: =前提!H12 -> 22 | I6: =前提!I12 -> 17 | ... M6: =前提!M12 -> 25 | N6: =SUM(B6:M6) -> 252
A7: 売上高 | B7: =前提!$B$5*B6/前提!$N$12 -> 72.5 | C7: =前提!$B$5*C6/前提!$N$12 -> 80.555556 | D7: =前提!$B$5*D6/前提!$N$12 -> 88.611111 | E7: =前提!$B$5*E6/前提!$N$12 -> 84.583333 | F7: =前提!$B$5*F6/前提!$N$12 -> 84.583333 | G7: =前提!$B$5*G6/前提!$N$12 -> 88.611111 | H7: =前提!$B$5*H6/前提!$N$12 -> 88.611111 | I7: =前提!$B$5*I6/前提!$N$12 -> 68.472222 | ... M7: =前提!$B$5*M6/前提!$N$12 -> 100.69444 | N7: =SUM(B7:M7) -> 1015
A8: 変動費 | B8: =-B7*前提!$B$7 -> -18.415 | C8: =-C7*前提!$B$7 -> -20.461111 | D8: =-D7*前提!$B$7 -> -22.507222 | E8: =-E7*前提!$B$7 -> -21.484167 | F8: =-F7*前提!$B$7 -> -21.484167 | G8: =-G7*前提!$B$7 -> -22.507222 | H8: =-H7*前提!$B$7 -> -22.507222 | I8: =-I7*前提!$B$7 -> -17.391944 | ... M8: =-M7*前提!$B$7 -> -25.576389 | N8: =SUM(B8:M8) -> -257.81
A9: 固定費 | B9: =-前提!$B$8 -> -19.099167 | C9: =-前提!$B$8 -> -19.099167 | D9: =-前提!$B$8 -> -19.099167 | E9: =-前提!$B$8 -> -19.099167 | F9: =-前提!$B$8 -> -19.099167 | G9: =-前提!$B$8 -> -19.099167 | H9: =-前提!$B$8 -> -19.099167 | I9: =-前提!$B$8 -> -19.099167 | ... M9: =-前提!$B$8 -> -19.099167 | N9: =SUM(B9:M9) -> -229.19
A10: 営業利益 | B10: =SUM(B7:B9) -> 34.985833 | C10: =SUM(C7:C9) -> 40.995278 | D10: =SUM(D7:D9) -> 47.004722 | E10: =SUM(E7:E9) -> 44 | F10: =SUM(F7:F9) -> 44 | G10: =SUM(G7:G9) -> 47.004722 | H10: =SUM(H7:H9) -> 47.004722 | I10: =SUM(I7:I9) -> 31.981111 | ... M10: =SUM(M7:M9) -> 56.018889 | N10: =SUM(B10:M10) -> 528
A12: 営業キャッシュフロー | B12: =B10 -> 34.985833 | C12: =C10 -> 40.995278 | D12: =D10 -> 47.004722 | E12: =E10 -> 44 | F12: =F10 -> 44 | G12: =G10 -> 47.004722 | H12: =H10 -> 47.004722 | I12: =I10 -> 31.981111 | ... M12: =M10 -> 56.018889 | N12: =SUM(B12:M12) -> 528
A13: 法人税等の納付 | B13: =IF(B4=2,-前提!$B$16,IF(B4=8,-前提!$B$17,0)) -> 0 | C13: =IF(C4=2,-前提!$B$16,IF(C4=8,-前提!$B$17,0)) -> -114 | D13: =IF(D4=2,-前提!$B$16,IF(D4=8,-前提!$B$17,0)) -> 0 | E13: =IF(E4=2,-前提!$B$16,IF(E4=8,-前提!$B$17,0)) -> 0 | F13: =IF(F4=2,-前提!$B$16,IF(F4=8,-前提!$B$17,0)) -> 0 | G13: =IF(G4=2,-前提!$B$16,IF(G4=8,-前提!$B$17,0)) -> 0 | H13: =IF(H4=2,-前提!$B$16,IF(H4=8,-前提!$B$17,0)) -> 0 | I13: =IF(I4=2,-前提!$B$16,IF(I4=8,-前提!$B$17,0)) -> -92 | ... M13: =IF(M4=2,-前提!$B$16,IF(M4=8,-前提!$B$17,0)) -> 0 | N13: =SUM(B13:M13) -> -206
A14: 支払利息 | B14: =IF(MOD(B4,3)=0,-前提!$B$22*前提!$B$23/4,0) -> 0 | C14: =IF(MOD(C4,3)=0,-B21*前提!$B$23/4,0) -> 0 | D14: =IF(MOD(D4,3)=0,-C21*前提!$B$23/4,0) -> -15 | E14: =IF(MOD(E4,3)=0,-D21*前提!$B$23/4,0) -> 0 | F14: =IF(MOD(F4,3)=0,-E21*前提!$B$23/4,0) -> 0 | G14: =IF(MOD(G4,3)=0,-F21*前提!$B$23/4,0) -> -14.625 | H14: =IF(MOD(H4,3)=0,-G21*前提!$B$23/4,0) -> 0 | I14: =IF(MOD(I4,3)=0,-H21*前提!$B$23/4,0) -> 0 | J14: =IF(MOD(J4,3)=0,-I21*前提!$B$23/4,0) -> -14.25 | ... M14: =IF(MOD(M4,3)=0,-L21*前提!$B$23/4,0) -> -13.875 | N14: =SUM(B14:M14) -> -57.75
A15: 借入元本の返済 | B15: =IF(MOD(B4,3)=0,-前提!$B$24,0) -> 0 | C15: =IF(MOD(C4,3)=0,-前提!$B$24,0) -> 0 | D15: =IF(MOD(D4,3)=0,-前提!$B$24,0) -> -50 | E15: =IF(MOD(E4,3)=0,-前提!$B$24,0) -> 0 | F15: =IF(MOD(F4,3)=0,-前提!$B$24,0) -> 0 | G15: =IF(MOD(G4,3)=0,-前提!$B$24,0) -> -50 | H15: =IF(MOD(H4,3)=0,-前提!$B$24,0) -> 0 | I15: =IF(MOD(I4,3)=0,-前提!$B$24,0) -> 0 | ... M15: =IF(MOD(M4,3)=0,-前提!$B$24,0) -> -50 | N15: =SUM(B15:M15) -> -200
A16: 当月収支 | B16: =SUM(B12:B15) -> 34.985833 | C16: =SUM(C12:C15) -> -73.004722 | D16: =SUM(D12:D15) -> -17.995278 | E16: =SUM(E12:E15) -> 44 | F16: =SUM(F12:F15) -> 44 | G16: =SUM(G12:G15) -> -17.620278 | H16: =SUM(H12:H15) -> 47.004722 | I16: =SUM(I12:I15) -> -60.018889 | ... M16: =SUM(M12:M15) -> -7.8561111 | N16: =SUM(B16:M16) -> 64.25
A18: 現金 期首残高 | B18: =前提!$B$25 -> 100 | C18: =B19 -> 134.98583 | D18: =C19 -> 61.981111 | E18: =D19 -> 43.985833 | F18: =E19 -> 87.985833 | G18: =F19 -> 131.98583 | H18: =G19 -> 114.36556 | I18: =H19 -> 161.37028 | J18: =I19 -> 101.35139 | ... M18: =L19 -> 172.10611 | N18: =B18 -> 100
A19: 現金 期末残高 | B19: =B18+B16 -> 134.98583 | C19: =C18+C16 -> 61.981111 | D19: =D18+D16 -> 43.985833 | E19: =E18+E16 -> 87.985833 | F19: =F18+F16 -> 131.98583 | G19: =G18+G16 -> 114.36556 | H19: =H18+H16 -> 161.37028 | I19: =I18+I16 -> 101.35139 | ... M19: =M18+M16 -> 164.25 | N19: =M19 -> 164.25
A21: 借入残高（期末） | B21: =前提!$B$22+B15 -> 2000 | C21: =B21+C15 -> 2000 | D21: =C21+D15 -> 1950 | E21: =D21+E15 -> 1950 | F21: =E21+F15 -> 1950 | G21: =F21+G15 -> 1900 | H21: =G21+H15 -> 1900 | I21: =H21+I15 -> 1900 | J21: =I21+J15 -> 1850 | ... M21: =L21+M15 -> 1800 | N21: =M21 -> 1800
A24: 最低現金残高 | B24: =MIN(B19:M19) -> 43.985833 | D24: ＝ 月次固定費の | E24: =B24/前提!$B$8 -> 2.3030237
A25: 年間の営業キャッシュフロー | B25: =N12 -> 528
A26: 年間の元利返済額 | B26: =-N14-N15 -> 257.75
A27: DSCR（法人税控除後のキャッシュフローベース） | B27: =(N12+N13)/B26 -> 1.2492726
A29: ※ 2月に2026年12月期の未払税金、8月に2027年度の中間納付が集中するため、3月末が年間で最も現金残高が薄くなる。
A30: ※ 減価償却費・設備投資・運転資本の増減はいずれも軽微なため、営業利益をそのまま営業キャッシュフローとみなしている。消費税は預り金の性質のため計上していない。

Sheet 買収資金
A1: 買収資金の調達と使途（譲受価額50.0億円のケース）
A2: 『前提』シートの留保現金を変更すると、中野氏の必要拠出額が自動で再計算される。
A4: 1. 資金使途（クロージング時）
A5: 株式譲受代金 | B5: 5000
A6: 取得関連費用 | B6: 150
A7: 合計 | B7: =SUM(B5:B6) -> 5150
A9: 2. 対象会社の現預金（2026年12月期末）
A10: 現預金 | B10: 1743
A11: 役員貸付金の回収（クロージング時に岸田氏が現金返済） | B11: 500
A12: 運転資金として留保する現金 | B12: =-前提!$B$25 -> -100
A13: ブリッジローンの返済原資 | B13: =SUM(B10:B12) -> 2143
A15: 3. 調達（クロージング時）
A16: みずほ銀行 タームローン | B16: =前提!$B$22 -> 2000
A17: みずほ銀行 ブリッジローン | B17: =B13 -> 2143
A18: 榊原氏 出資 | B18: 1000
A19: 中野氏 出資（資本金10万円）＋株主貸付 | B19: =B7-B16-B17-B18 -> 7
A20: 合計 | B20: =SUM(B16:B19) -> 5150
A22: 差引（ゼロであること） | B22: =B7-B20 -> 0
A24: 合併後の有利子負債 | B24: =B16 -> 2000
A25: 合併後の現預金 | B25: =前提!$B$25 -> 100
A26: ネットデット | B26: =B24-B25 -> 1900
A27: ネットデット／EBITDA | B27: =B26/529 -> 3.5916824
A29: ※ ブリッジローンはクロージング後、対象会社の余剰現預金をもって全額返済する。 ※ 留保する現金を1億円増やすと、中野氏の必要拠出額も1億円増え、2027年の最低現金残高も1億円増える（1対1の関係）。
A30: ※ EBITDAは2026年12月期計画の529百万円。
