Workbook

Sheet 前提
A1: WineBank ワインマイル｜前提条件
A2: 青字＝入力値（変更可）／黒字＝数式。単位：万円
A4: ■ 販売ミックス
A5: ランク | B5: 単価 | C5: 人数 | D5: 販売額 | E5: マイル還元率 | F5: マイル発行額
A6: PRESTIGE | B6: 100 | C6: 52 | D6: =B6*C6 -> 5200 | E6: 0.035 | F6: =D6*E6 -> 182
A7: GOLD | B7: 400 | C7: 7 | D7: =B7*C7 -> 2800 | E7: 0.045 | F7: =D7*E7 -> 126
A8: SIGNATURE | B8: 1000 | C8: 2 | D8: =B8*C8 -> 2000 | E8: 0.055 | F8: =D8*E8 -> 110
A9: 合計 | C9: =SUM(C6:C8) -> 61 | D9: =SUM(D6:D8) -> 10000 | E9: =IF(D9=0,0,F9/D9) -> 0.0418 | F9: =SUM(F6:F8) -> 418 | G9: ← 還元率3.5〜5.5%の加重平均＝マイル発行の額面率
A11: ■ 事業前提
A12: ワイン値上がり率（年） | B12: 0.06 | G12: P1ファンド実績・経費控除後
A13: 借入金利（年） | B13: 0.03 | G13: 自社在庫の調達コスト
A14: 保管料・保険料（円/本/年） | B14: 210 | G14: 鈴与実額。倉持案は1億=7,619本で年160万 → 210円/本
A15: 平均単価（円/本） | B15: 20000 | G15: ネット最安値ベース。単価が高いほど本数が減り保管料率は下がる
A16: 販売粗利率 | B16: 0.3 | G16: 売価ベース。原価率は70%
A17: 管理手数料率（年） | B17: 0.025 | G17: 預かり資産に対して。簿価ベース
A18: 成功報酬率 | B18: 0.25 | G18: 値上がり益に対して。契約終了時に精算
A19: 期首ワイン在庫（簿価） | B19: 10000 | G19: 自社保有分
A20: 新規買付額 | B20: 12000 | G20: 販売代金を原資に買い増す額
A21: オークション年間回転率 | B21: 0.1 | G21: 預かり資産のうち年間で売却される割合
A22: うち当社ルート比率 | B22: 0.5 | G22: 他ルートでの売却もあるため保守的に半分
A23: 買い手手数料率 | B23: 0.1 | G23: 売り手からは取らない。買い手のみ10%
A24: 保管料率（対 預かり資産） | B24: =B14/B15 -> 0.0105 | G24: ← 210円 ÷ 20,000円 ＝ 1.05%。従来置いていた1.5%より軽い
A26: ■ マイル交換ミックス（どこで使われるかの想定）
A27: 交換先 | B27: 構成比 | C27: 交換レート | D27: 当社原価率
A28: 系列レストラン | B28: 0.25 | C28: 1 | D28: 0.9 | G28: 額面×1.0×90%保証
A29: グランメゾン | B29: 0.18 | C29: 0.5 | D29: 0.45 | G29: 額面×0.5×90%保証
A30: WineBank CLUB 会費充当 | B30: 0.12 | C30: 1 | D30: 0 | G30: 内部振替。現金流出なし
A31: オークション成約手数料 | B31: 0.12 | C31: 1 | D31: 0 | G31: 手数料の免除。現金流出なし
A32: ワインスクール受講料 | B32: 0.1 | C32: 1 | D32: 0.5 | G32: 講師・会場費
A33: 会員交流イベント参加費 | B33: 0.08 | C33: 1 | D33: 0.5 | G33: 会場・飲食費
A34: ワイン追加購入 | B34: 0.05 | C34: 1 | D34: 0.8 | G34: ワインの仕入原価
A35: 失効 | B35: 0.1 | C35: 0 | D35: 0 | G35: 未使用のまま期限到来
A36: 合計 / 加重平均 | B36: =SUM(B28:B35) -> 1 | D36: =SUMPRODUCT(B28:B35,D28:D35) -> 0.436 | G36: ← これが「マイル原価率」。構成比の合計は100%にすること

Sheet マイル計算
A1: マイル計算｜額面（3.5〜5.5%）→ PL上の実費用の橋渡し
A2: 会員から見た還元率と、当社のPLに乗る費用は別物です。差は「どこで使われるか」で決まります。
A4: STEP 1｜ランク別のマイル発行額（額面）
A5: ランク | B5: 販売額 | C5: 還元率 | D5: マイル発行額
A6: =前提!A6 -> PRESTIGE | B6: =前提!D6 -> 5200 | C6: =前提!E6 -> 0.035 | D6: =B6*C6 -> 182
A7: =前提!A7 -> GOLD | B7: =前提!D7 -> 2800 | C7: =前提!E7 -> 0.045 | D7: =B7*C7 -> 126
A8: =前提!A8 -> SIGNATURE | B8: =前提!D8 -> 2000 | C8: =前提!E8 -> 0.055 | D8: =B8*C8 -> 110
A9: 合計 | B9: =SUM(B6:B8) -> 10000 | C9: =IF(B9=0,0,D9/B9) -> 0.0418 | D9: =SUM(D6:D8) -> 418 | F9: ← 額面の発行率。会員が「還元率」として認識する数字
A11: STEP 2｜交換先ごとに、実際に出ていく金額
A12: 交換先 | B12: 構成比 | C12: 額面 | D12: 原価率 | E12: 実費用
A13: =前提!A28 -> 系列レストラン | B13: =前提!B28 -> 0.25 | C13: =$D$9*B13 -> 104.5 | D13: =前提!D28 -> 0.9 | E13: =C13*D13 -> 94.05
A14: =前提!A29 -> グランメゾン | B14: =前提!B29 -> 0.18 | C14: =$D$9*B14 -> 75.24 | D14: =前提!D29 -> 0.45 | E14: =C14*D14 -> 33.858
A15: =前提!A30 -> WineBank CLUB 会費充当 | B15: =前提!B30 -> 0.12 | C15: =$D$9*B15 -> 50.16 | D15: =前提!D30 -> 0 | E15: =C15*D15 -> 0
A16: =前提!A31 -> オークション成約手数料 | B16: =前提!B31 -> 0.12 | C16: =$D$9*B16 -> 50.16 | D16: =前提!D31 -> 0 | E16: =C16*D16 -> 0
A17: =前提!A32 -> ワインスクール受講料 | B17: =前提!B32 -> 0.1 | C17: =$D$9*B17 -> 41.8 | D17: =前提!D32 -> 0.5 | E17: =C17*D17 -> 20.9
A18: =前提!A33 -> 会員交流イベント参加費 | B18: =前提!B33 -> 0.08 | C18: =$D$9*B18 -> 33.44 | D18: =前提!D33 -> 0.5 | E18: =C18*D18 -> 16.72
A19: =前提!A34 -> ワイン追加購入 | B19: =前提!B34 -> 0.05 | C19: =$D$9*B19 -> 20.9 | D19: =前提!D34 -> 0.8 | E19: =C19*D19 -> 16.72
A20: =前提!A35 -> 失効 | B20: =前提!B35 -> 0.1 | C20: =$D$9*B20 -> 41.8 | D20: =前提!D35 -> 0 | E20: =C20*D20 -> 0
A21: 合計 / 加重平均 | B21: =SUM(B13:B20) -> 1 | C21: =SUM(C13:C20) -> 418 | D21: =IF(C21=0,0,E21/C21) -> 0.436 | E21: =SUM(E13:E20) -> 182.248 | F21: ← マイル原価率（加重平均）と、PLに乗る実費用
A23: STEP 3｜まとめ
A24: 会員が受け取る額面（対 販売額） | B24: =IF(B9=0,0,D9/B9) -> 0.0418 | F24: 会員から見た還元率
A25: マイル原価率（加重平均） | B25: =D21 -> 0.436 | F25: 額面100に対して実際に出ていく割合
A26: PL上の実費用（対 販売額） | B26: =IF(B9=0,0,E21/B9) -> 0.0182248 | F26: ＝ 額面率 × 原価率。これがPLに乗る
A27: PL上の実費用（金額） | B27: =E21 -> 182.248

Sheet 損益計算書
A1: 損益計算書｜WineBank単体
A2: 初年度＝1億販売＋1.2億買付／2年目以降＝追加販売なし。手数料・マイルとも簿価ベース。単位：万円
B4: 初年度 | C4: 2年目以降
A5: 【売上高】
A6: ワイン販売売上 | B6: =前提!D9 -> 10000 | C6: 0 | E6: 1億円分を販売
A7: 管理手数料収入 | B7: =前提!D9*前提!B17 -> 250 | C7: =前提!D9*前提!B17 -> 250 | E7: 預かり資産（簿価）× 2.5%
A8: 売上高 計 | B8: =SUM(B6:B7) -> 10250 | C8: =SUM(C6:C7) -> 250
A9: 【売上原価】
A10: ワイン売上原価 | B10: =-B6*(1-前提!B16) -> -7000 | C10: 0 | E10: 粗利率30% → 原価率70%
A11: 売上総利益 | B11: =B8+B10 -> 3250 | C11: =C8+C10 -> 250
A12: 【販売費及び一般管理費】
A13: マイル費用 | B13: =-マイル計算!E21 -> -182.248 | C13: =-マイル計算!E21 -> -182.248 | E13: 額面418 × 原価率43.6%
A14: 保管料・保険料（預かり資産） | B14: =-前提!D9*前提!B14/前提!B15 -> -105 | C14: =-前提!D9*前提!B14/前提!B15 -> -105 | E14: 本数×210円（鈴与実額）
A15: 保管料・保険料（自社在庫） | B15: =-(前提!B19+前提!B20+B10)*前提!B14/前提!B15 -> -157.5 | C15: 0 | E15: 期末自社在庫にも同率を適用
A16: 販管費 計 | B16: =SUM(B13:B15) -> -444.748 | C16: =SUM(C13:C15) -> -287.248
A17: 営業利益 | B17: =B11+B16 -> 2805.252 | C17: =C11+C16 -> -37.248
A18: 【営業外】
A19: 支払利息 | B19: =-(前提!B19+MAX(0,前提!B20-B6))*前提!B13 -> -360 | C19: 0 | E19: 期末借入 × 3%
A20: オークション収益 | B20: =前提!D9*前提!B21*前提!B22*前提!B23 -> 50 | C20: =前提!D9*前提!B21*前提!B22*前提!B23 -> 50 | E20: 回転率×当社ルート50%×買い手10%
A21: 経常利益 | B21: =B17+B19+B20 -> 2495.252 | C21: =C17+C19+C20 -> 12.752
A23: （参考）成功報酬の年平均発生額 | B23: =前提!D9*((1+前提!B12)^5-1)*前提!B18/5 -> 169.11279 | C23: =前提!D9*((1+前提!B12)^5-1)*前提!B18/5 -> 169.11279 | E23: 5年保有・値上がり益25%を年割り
A24: 経常利益 ＋ 成功報酬発生 | B24: =B21+B23 -> 2664.3648 | C24: =C21+C23 -> 181.86479
A26: ■ 損益分岐：マイル原価率が何%を超えるとストックだけで赤字になるか
A27: （管理手数料 − 保管料 ＋ オークション収益）÷ マイル発行額 | B27: =(C7+C14+C20)/マイル計算!D9 -> 0.46650718 | E27: ← 前提シート B36 の想定原価率と比較
A28: 現在の想定マイル原価率 | B28: =マイル計算!D21 -> 0.436
A29: 判定 | B29: =IF(B28<=B27,"OK：ストックのみで黒字","要改善：ストックのみでは赤字") -> OK：ストックのみで黒字
