Workbook

Sheet 前提
A1: 前提条件（青字＝入力値）
A2: 出典：合意書（2026年9月）／資本政策202609（投資家様）／事業収支資料20260904／5か年事業計画FY2027-2031
A4: ■ 現在の株主構成（2026年9月末）
A5: 中野邦人 保有株数 | B5: 1300 | D5: 資本政策202609より
A6: 合同会社WineBank P3（WBP3）保有株数 | B6: 700 | D6: アピシウスの株主。対象会社の直接株主はこの2者のみ
A7: 資本金（千円） | B7: 10000 | D7: 資本政策202609より
A8: 資本準備金（千円） | B8: 0
A9: 現在の発行済株式総数 | B9: =B5+B6 -> 2000
A11: ■ 第三者割当①（2026年10月末＝本件実行日）
A12: 1株あたり発行価額（円） | B12: 150000 | D12: Preバリュー300,000,000円 ÷ 現在2,000株＝@150,000円
A13: 投資家A（AnyColorオーナー）割当株数 | B13: 133 | D13: 合意書は「金20,000,000円」。@150,000では133.33株となり端数が出る（後掲チェック参照）
A14: 投資家B 割当株数 | B14: 267 | D14: 4,000万円枠。266.67株を切上げ
A15: 投資家C 割当株数 | B15: 400 | D15: 6,000万円枠。端数なし
A16: 投資家D 割当株数 | B16: 200 | D16: 3,000万円枠。端数なし
A17: 資本金への計上割合 | B17: 0.5 | D17: 残額は資本準備金へ（会社法445条2項・3項）
A18: 割当株数 計 | B18: =SUM(B13:B16) -> 1000
A19: 本件出資総額（円） | B19: =B18*B12 -> 150000000 | D19: 合意書：総額150,000,000円の募集
A21: ■ ストックオプション（2028年想定）
A22: SO付与株数（潜在株式） | B22: 300 | D22: 資本政策202609の備考「潜在株10％以内」を発行済3,000株の10％として設定
A24: ■ 第三者割当②（2029年・想定枠）
A25: 割当株数 | B25: 0 | D25: 事業収支資料p11「調達金額2.0-3.0億円」を実現する場合の枠。バリュエーション未確定のため0で設定
A26: 1株あたり発行価額（円） | B26: 0 | D26: 旧資本政策の@192,000円は前回@150,000円より高いが、2027年の@50,000円はダウンラウンドで整合しない
A28: ■ 合意書の確約条件
A29: 甲側 持株比率の下限 | B29: 0.66 | D29: 合意書 第2条3項3号。現行文は「WBP3の持株比率」だがWBP3単独は23.3%。中野邦人との合計と解する
A30: 外部投資家 比率（合意書表記） | B30: 0.34 | D30: 合意書「本件34％投資家」。実際の外部合計は33.3%
A31: 投資家A 出資額（合意書記載・円） | B31: 20000000 | D31: 合意書 第1条1項
A32: Preバリュー（合意書記載・円） | B32: 300000000 | D32: 合意書 第1条1項
A33: 本件出資総額（合意書記載・円） | B33: 150000000 | D33: 合意書 第1条1項

Sheet 資本政策
A1: 株式会社Brasserie Thierry Marx 資本政策（修正版）
A2: 単位：株／円。青字＝「前提」シートの入力値に連動。※旧版の「株式譲渡」列見出しは実態（第三者割当増資）に合わせて修正済み
C3: 現在 2026年9月末 | E3: 第三者割当① 2026年10月末（本件実行日） | I3: SO付与 2028年 | K3: 第三者割当② 2029年（想定枠）
A4: No | B4: 株主 | C4: 株数 | D4: 比率 | E4: 割当株数 | F4: 払込金額(円) | G4: 発行済株数 | H4: 比率 | I4: 潜在込株数 | J4: 潜在込比率 | K4: 割当株数 | L4: 潜在込株数 | M4: 潜在込比率
A5: 1 | B5: 中野邦人 | C5: =前提!$B$5 -> 1300 | D5: =IF($C$14=0,0,C5/$C$14) -> 0.65 | E5: 0 | F5: =E5*前提!$B$12 -> 0 | G5: =C5+E5 -> 1300 | H5: =IF($G$14=0,0,G5/$G$14) -> 0.43333333 | I5: =G5 -> 1300 | J5: =IF($I$14=0,0,I5/$I$14) -> 0.39393939 | K5: 0 | L5: =I5+K5 -> 1300 | M5: =IF($L$14=0,0,L5/$L$14) -> 0.39393939
A6: 2 | B6: 合同会社WineBank P3（WBP3） | C6: =前提!$B$6 -> 700 | D6: =IF($C$14=0,0,C6/$C$14) -> 0.35 | E6: 0 | F6: =E6*前提!$B$12 -> 0 | G6: =C6+E6 -> 700 | H6: =IF($G$14=0,0,G6/$G$14) -> 0.23333333 | I6: =G6 -> 700 | J6: =IF($I$14=0,0,I6/$I$14) -> 0.21212121 | K6: 0 | L6: =I6+K6 -> 700 | M6: =IF($L$14=0,0,L6/$L$14) -> 0.21212121
B7: 小計 甲側（中野＋WBP3） | C7: =SUM(C5:C6) -> 2000 | D7: =IF($C$14=0,0,C7/$C$14) -> 1 | E7: =SUM(E5:E6) -> 0 | F7: =E7*前提!$B$12 -> 0 | G7: =C7+E7 -> 2000 | H7: =IF($G$14=0,0,G7/$G$14) -> 0.66666667 | I7: =SUM(I5:I6) -> 2000 | J7: =IF($I$14=0,0,I7/$I$14) -> 0.60606061 | K7: 0 | L7: =I7+K7 -> 2000 | M7: =IF($L$14=0,0,L7/$L$14) -> 0.60606061
A8: 3 | B8: 投資家A（AnyColorオーナー） | C8: 0 | D8: =IF($C$14=0,0,C8/$C$14) -> 0 | E8: =前提!$B$13 -> 133 | F8: =E8*前提!$B$12 -> 19950000 | G8: =C8+E8 -> 133 | H8: =IF($G$14=0,0,G8/$G$14) -> 0.044333333 | I8: =G8 -> 133 | J8: =IF($I$14=0,0,I8/$I$14) -> 0.04030303 | K8: 0 | L8: =I8+K8 -> 133 | M8: =IF($L$14=0,0,L8/$L$14) -> 0.04030303
A9: 4 | B9: 投資家B | C9: 0 | D9: =IF($C$14=0,0,C9/$C$14) -> 0 | E9: =前提!$B$14 -> 267 | F9: =E9*前提!$B$12 -> 40050000 | G9: =C9+E9 -> 267 | H9: =IF($G$14=0,0,G9/$G$14) -> 0.089 | I9: =G9 -> 267 | J9: =IF($I$14=0,0,I9/$I$14) -> 0.080909091 | K9: 0 | L9: =I9+K9 -> 267 | M9: =IF($L$14=0,0,L9/$L$14) -> 0.080909091
A10: 5 | B10: 投資家C | C10: 0 | D10: =IF($C$14=0,0,C10/$C$14) -> 0 | E10: =前提!$B$15 -> 400 | F10: =E10*前提!$B$12 -> 60000000 | G10: =C10+E10 -> 400 | H10: =IF($G$14=0,0,G10/$G$14) -> 0.13333333 | I10: =G10 -> 400 | J10: =IF($I$14=0,0,I10/$I$14) -> 0.12121212 | K10: 0 | L10: =I10+K10 -> 400 | M10: =IF($L$14=0,0,L10/$L$14) -> 0.12121212
A11: 6 | B11: 投資家D | C11: 0 | D11: =IF($C$14=0,0,C11/$C$14) -> 0 | E11: =前提!$B$16 -> 200 | F11: =E11*前提!$B$12 -> 30000000 | G11: =C11+E11 -> 200 | H11: =IF($G$14=0,0,G11/$G$14) -> 0.066666667 | I11: =G11 -> 200 | J11: =IF($I$14=0,0,I11/$I$14) -> 0.060606061 | K11: 0 | L11: =I11+K11 -> 200 | M11: =IF($L$14=0,0,L11/$L$14) -> 0.060606061
B12: 小計 外部投資家 | C12: =SUM(C8:C11) -> 0 | D12: =IF($C$14=0,0,C12/$C$14) -> 0 | E12: =SUM(E8:E11) -> 1000 | F12: =E12*前提!$B$12 -> 150000000 | G12: =C12+E12 -> 1000 | H12: =IF($G$14=0,0,G12/$G$14) -> 0.33333333 | I12: =SUM(I8:I11) -> 1000 | J12: =IF($I$14=0,0,I12/$I$14) -> 0.3030303 | K12: =前提!$B$25 -> 0 | L12: =I12+K12 -> 1000 | M12: =IF($L$14=0,0,L12/$L$14) -> 0.3030303
B13: ストックオプション（未行使） | C13: 0 | D13: =IF($C$14=0,0,C13/$C$14) -> 0 | E13: 0 | F13: =E13*前提!$B$12 -> 0 | G13: =C13+E13 -> 0 | H13: =IF($G$14=0,0,G13/$G$14) -> 0 | I13: =前提!$B$22 -> 300 | J13: =IF($I$14=0,0,I13/$I$14) -> 0.090909091 | K13: 0 | L13: =I13+K13 -> 300 | M13: =IF($L$14=0,0,L13/$L$14) -> 0.090909091
B14: 合 計 | C14: =C7+C12 -> 2000 | D14: =IF($C$14=0,0,C14/$C$14) -> 1 | E14: =E7+E12 -> 1000 | F14: =E14*前提!$B$12 -> 150000000 | G14: =C14+E14 -> 3000 | H14: =IF($G$14=0,0,G14/$G$14) -> 1 | I14: =I7+I12+I13 -> 3300 | J14: =IF($I$14=0,0,I14/$I$14) -> 1 | K14: =K7+K12 -> 0 | L14: =I14+K14 -> 3300 | M14: =IF($L$14=0,0,L14/$L$14) -> 1
B16: 1株あたり発行価額（円） | E16: =前提!$B$12 -> 150000 | K16: =前提!$B$26 -> 0
B17: 調達額（円） | E17: =F14 -> 150000000 | K17: =K14*前提!$B$26 -> 0
B18: Pre-money（円） | E18: =C14*前提!$B$12 -> 300000000 | K18: =I14*前提!$B$26 -> 0
B19: Post-money（円） | E19: =G14*前提!$B$12 -> 450000000 | K19: =L14*前提!$B$26 -> 0
B20: 資本金（円） | C20: =前提!$B$7*1000 -> 10000000 | E20: =C20+F14*前提!$B$17 -> 85000000
B21: 資本準備金（円） | C21: =前提!$B$8*1000 -> 0 | E21: =C21+F14*(1-前提!$B$17) -> 75000000
B23: ▼ 旧版からの主な修正点
B24: ① 2028年以降で投資家A（134株）が「潜在株式考慮後」から消え、合計が3,000→2,866株に減っていた計算式の破損を修正
B25: ② SO付与株数が0のままだったため、備考「潜在株10％以内」に沿って300株を計上（潜在込3,300株）
B26: ③ 2026年12月末の列見出し「株式譲渡」を実態（第三者割当増資）に修正。払込期日は合意書に合わせ2026年10月末に統一
B27: ④ 2027年の@50,000円（前回@150,000円に対するダウンラウンド）を削除。2029年は価額未確定のため空欄の想定枠に
B28: ⑤ 備考欄のWineBank本体の記載（ワインファンド、375株中野移転、有限会社中村→WineBank商号変更）を削除
B29: ⑥ 社名表記「Thieery」→「Thierry」に修正

Sheet 合意書整合チェック
A1: 合意書との整合チェック
A2: 合意書（2026年9月）記載値と本資本政策の突合。判定は自動計算。
A3: チェック項目 | B3: 合意書の記載 | C3: 本資本政策 | D3: 差 | E3: 判定 | G3: コメント
A4: 投資家Aの出資額 | B4: =前提!$B$31 -> 20000000 | C4: =資本政策!F8 -> 19950000 | D4: =C4-B4 -> -50000 | E4: =IF(ABS(D4)<0.0000001,"OK","要修正") -> 要修正 | G4: @150,000円では20,000,000円が割り切れない（133.33株）。133株なら19,950,000円、134株なら20,100,000円。合意書の金額か株数の調整が必要
A5: 本件出資総額 | B5: =前提!$B$33 -> 150000000 | C5: =資本政策!F14 -> 150000000 | D5: =C5-B5 -> 0 | E5: =IF(ABS(D5)<0.0000001,"OK","要修正") -> OK | G5: 133/267/400/200株の構成で総額はちょうど150,000,000円
A6: Pre-money | B6: =前提!$B$32 -> 300000000 | C6: =資本政策!E18 -> 300000000 | D6: =C6-B6 -> 0 | E6: =IF(ABS(D6)<0.0000001,"OK","要修正") -> OK | G6: 一致
A7: 甲側持株比率（発行済ベース） | B7: =前提!$B$29 -> 0.66 | C7: =資本政策!H7 -> 0.66666667 | D7: =C7-B7 -> 0.0066666667 | E7: =IF(C7>=B7-0.0000001,"OK","要修正") -> OK | G7: 合意書 第2条3項3号。現行条文は「WBP3の持株比率」だがWBP3単独は23.3％。「中野邦人及びWBP3の合計」への修正が必要
A8: 甲側持株比率（SO発行後・潜在込） | B8: =前提!$B$29 -> 0.66 | C8: =資本政策!J7 -> 0.60606061 | D8: =C8-B8 -> -0.053939394 | E8: =IF(C8>=B8-0.0000001,"OK","要修正") -> 要修正 | G8: SO300株を発行すると60.6％となり66％を下回る。合意書に「発行済株式ベース」と明記しない限りSO発行が確約違反になりうる
A9: 外部投資家 合計比率 | B9: =前提!$B$30 -> 0.34 | C9: =資本政策!H12 -> 0.33333333 | D9: =C9-B9 -> -0.0066666667 | E9: =IF(ABS(D9)<0.0000001,"OK","要修正") -> 要修正 | G9: 合意書の「本件34％投資家」は実際には33.3％。単独34％の投資家は存在せず（最大は投資家Cの13.3％）、定義規定も本文にない
A11: ■ 66％条項による追加エクイティ調達余地
A12: 甲側は2,000株で固定（今回ラウンドで追加出資なし）。66％を維持できる発行済株式総数の上限から逆算。
A13: 甲側 保有株数（固定） | B13: =資本政策!G7 -> 2000
A14: 66％維持時の発行済株式総数 上限 | B14: =資本政策!G7/前提!$B$29 -> 3030.303 | G14: ＝甲側株数 ÷ 66％
A15: 第三者割当①後の発行済株式総数 | B15: =資本政策!G14 -> 3000
A16: 追加発行できる株数 | B16: =B14-B15 -> 30.30303 | G16: 上限 － 現在。マイナスなら既に抵触
A17: @150,000円での追加調達可能額（円） | B17: =B16*前提!$B$12 -> 4545454.5 | G17: 追加発行株数 × @150,000円
A19: → 事業収支資料p11「調達金額2.0-3.0億円」は、合意書の66％条項の下では達成不能。
A20: 2億円を30株で調達するには@6,666,667円/株（現行の44倍）が必要。甲側の同時出資、66％の緩和、
A21: または「本件ラウンド時点の比率」への限定のいずれかが必須。種類株式の発行禁止（第2条3項4号）も併せて要見直し。

Sheet 資金需要
A1: 資金需要と調達の突合（単位：百万円）
A2: 出典：5か年事業計画FY2027-2031（六本木1号店＋9店舗連結）。青字＝同計画からの転記値
A3: 項 目 | B3: FY2027 | C3: FY2028 | D3: FY2029 | E3: FY2030 | F3: FY2031 | G3: 5年累計
A4: 連結EBITDA | B4: 37.4 | C4: 103.5 | D4: 233.7 | E4: 377.9 | F4: 523.2 | G4: =SUM(B4:F4) -> 1275.7
A5: 投資キャッシュアウト | B5: -123.7 | C5: -251.3 | D5: -272.5 | E5: -303.7 | F5: -334.9 | G5: =SUM(B5:F5) -> -1286.1
A6: 営業利益 | B6: 16.6 | C6: 56.7 | D6: 145.9 | E6: 249.6 | F6: 354.2 | G6: =SUM(B6:F6) -> 823
A7: （前提）法人税 実効税率 ※B列セルが入力値 | B7: 0.3 | I7: 簡易。繰越欠損金の控除は考慮せず
A8: 法人税等（推計） | B8: =-MAX(0,B6)*$B$7 -> -4.98 | C8: =-MAX(0,C6)*$B$7 -> -17.01 | D8: =-MAX(0,D6)*$B$7 -> -43.77 | E8: =-MAX(0,E6)*$B$7 -> -74.88 | F8: =-MAX(0,F6)*$B$7 -> -106.26 | G8: =SUM(B8:F8) -> -246.9
A9: 税引後フリーキャッシュフロー | B9: =B4+B5+B8 -> -91.28 | C9: =C4+C5+C8 -> -164.81 | D9: =D4+D5+D8 -> -82.57 | E9: =E4+E5+E8 -> -0.68 | F9: =F4+F5+F8 -> 82.04 | G9: =SUM(B9:F9) -> -257.3
A10: 累計フリーキャッシュフロー | B10: =B9 -> -91.28 | C10: =B10+C9 -> -256.09 | D10: =C10+D9 -> -338.66 | E10: =D10+E9 -> -339.34 | F10: =E10+F9 -> -257.3
A12: ■ 必要調達額との比較
A13: 最大資金需要（累計FCFの最小値） | B13: =-MIN(B10:F10) -> 339.34 | I13: 税引後ベース。FY2029末が底
A14: 既存調達額（エクイティ＋デット） | B14: 200 | I14: 事業収支資料p11「2億調達済み」。内訳未確認のため要確認
A15: 第三者割当①（今回） | B15: =資本政策!F14/1000000 -> 150 | I15: ＝資本政策の本件出資総額
A16: 調達額 計 | B16: =B14+B15 -> 350
A17: 差（プラスがバッファ） | B17: =B16-B13 -> 10.66 | I17: デットの元本返済・分割弁済に係る金利相当は未考慮
A19: → バッファは1億円未満。既存2億円にデットが含まれるため、その元本返済を入れると不足に転じる可能性がある。
A20: ※ 対象会社は六本木1号店の運営会社。上記は9店舗連結の計画値。2号店以降を対象会社で持つのか別会社にするのかを
A21: 明確にしないと、投資家が見るバリュエーション（Post4.5億）と出資対象の事業範囲が一致しない。
